{
"meta":{"test_sets":[],"test_metrics":[],"learn_metrics":[{"best_value":"Min","name":"RMSE"}],"launch_mode":"Train","parameters":"","iteration_count":1000,"learn_sets":["learn"],"name":"experiment"},
"iterations":[
{"learn":[21.85288272],"iteration":0,"passed_time":0.2364366617,"remaining_time":236.2002251},
{"learn":[21.44175964],"iteration":1,"passed_time":0.2941707227,"remaining_time":146.7911906},
{"learn":[21.12195191],"iteration":2,"passed_time":0.3468474973,"remaining_time":115.2689849},
{"learn":[20.79375908],"iteration":3,"passed_time":0.4020013919,"remaining_time":100.0983466},
{"learn":[20.47275123],"iteration":4,"passed_time":0.4596242855,"remaining_time":91.46523281},
{"learn":[20.14634166],"iteration":5,"passed_time":0.5143893126,"remaining_time":85.21716279},
{"learn":[19.82717429],"iteration":6,"passed_time":0.5663525149,"remaining_time":80.34114962},
{"learn":[19.56507071],"iteration":7,"passed_time":0.6179030882,"remaining_time":76.61998294},
{"learn":[19.31134937],"iteration":8,"passed_time":0.6695909093,"remaining_time":73.72939902},
{"learn":[19.06021256],"iteration":9,"passed_time":0.7221967064,"remaining_time":71.49747393},
{"learn":[18.85699342],"iteration":10,"passed_time":0.7717648784,"remaining_time":69.38867861},
{"learn":[18.62377864],"iteration":11,"passed_time":0.822191905,"remaining_time":67.69380018},
{"learn":[18.438353],"iteration":12,"passed_time":0.8729129045,"remaining_time":66.2742336},
{"learn":[18.25121117],"iteration":13,"passed_time":0.9281985239,"remaining_time":65.37169604},
{"learn":[18.04439635],"iteration":14,"passed_time":0.9892968837,"remaining_time":64.96382869},
{"learn":[17.87899496],"iteration":15,"passed_time":1.047568649,"remaining_time":64.42547193},
{"learn":[17.7142797],"iteration":16,"passed_time":1.104890381,"remaining_time":63.88866145},
{"learn":[17.52765603],"iteration":17,"passed_time":1.163484661,"remaining_time":63.47455205},
{"learn":[17.37360861],"iteration":18,"passed_time":1.220126628,"remaining_time":62.99706433},
{"learn":[17.2549521],"iteration":19,"passed_time":1.273666969,"remaining_time":62.40968148},
{"learn":[17.11348455],"iteration":20,"passed_time":1.327889561,"remaining_time":61.9049467},
{"learn":[16.98031647],"iteration":21,"passed_time":1.383288999,"remaining_time":61.49348366},
{"learn":[16.86851704],"iteration":22,"passed_time":1.443224294,"remaining_time":61.30565806},
{"learn":[16.75385819],"iteration":23,"passed_time":1.49684228,"remaining_time":60.87158606},
{"learn":[16.64187399],"iteration":24,"passed_time":1.550770638,"remaining_time":60.48005488},
{"learn":[16.52781494],"iteration":25,"passed_time":1.604941417,"remaining_time":60.12357462},
{"learn":[16.4377895],"iteration":26,"passed_time":1.662485509,"remaining_time":59.91105186},
{"learn":[16.32481648],"iteration":27,"passed_time":1.717392694,"remaining_time":59.61806066},
{"learn":[16.21196772],"iteration":28,"passed_time":1.768095632,"remaining_time":59.20071927},
{"learn":[16.08861065],"iteration":29,"passed_time":1.817509146,"remaining_time":58.76612907},
{"learn":[15.98470042],"iteration":30,"passed_time":1.87184221,"remaining_time":58.51016456},
{"learn":[15.87988605],"iteration":31,"passed_time":1.924837453,"remaining_time":58.22633296},
{"learn":[15.79438945],"iteration":32,"passed_time":1.978892284,"remaining_time":57.98754058},
{"learn":[15.69290244],"iteration":33,"passed_time":2.028296051,"remaining_time":57.62747017},
{"learn":[15.61327058],"iteration":34,"passed_time":2.077842931,"remaining_time":57.28909794},
{"learn":[15.52576214],"iteration":35,"passed_time":2.127316669,"remaining_time":56.96481301},
{"learn":[15.44173977],"iteration":36,"passed_time":2.17661228,"remaining_time":56.65074665},
{"learn":[15.37830755],"iteration":37,"passed_time":2.226718566,"remaining_time":56.37113844},
{"learn":[15.31604668],"iteration":38,"passed_time":2.276155588,"remaining_time":56.08680821},
{"learn":[15.23862549],"iteration":39,"passed_time":2.326741681,"remaining_time":55.84180034},
{"learn":[15.1909517],"iteration":40,"passed_time":2.379664994,"remaining_time":55.66094461},
{"learn":[15.11767829],"iteration":41,"passed_time":2.431774701,"remaining_time":55.46762295},
{"learn":[15.05659629],"iteration":42,"passed_time":2.485407914,"remaining_time":55.31477613},
{"learn":[14.98242016],"iteration":43,"passed_time":2.537887596,"remaining_time":55.14137596},
{"learn":[14.91586471],"iteration":44,"passed_time":2.591396107,"remaining_time":54.99518404},
{"learn":[14.8357871],"iteration":45,"passed_time":2.642138084,"remaining_time":54.79564634},
{"learn":[14.75471709],"iteration":46,"passed_time":2.694846929,"remaining_time":54.64232176},
{"learn":[14.69931839],"iteration":47,"passed_time":2.745903656,"remaining_time":54.4604225},
{"learn":[14.65603875],"iteration":48,"passed_time":2.797329785,"remaining_time":54.29103318},
{"learn":[14.6042706],"iteration":49,"passed_time":2.850451644,"remaining_time":54.15858123},
{"learn":[14.55244035],"iteration":50,"passed_time":2.901274802,"remaining_time":53.98646641},
{"learn":[14.4914092],"iteration":51,"passed_time":2.954935286,"remaining_time":53.87074328},
{"learn":[14.43876342],"iteration":52,"passed_time":3.005718302,"remaining_time":53.70594777},
{"learn":[14.39451507],"iteration":53,"passed_time":3.057474053,"remaining_time":53.56241582},
{"learn":[14.34202615],"iteration":54,"passed_time":3.109746451,"remaining_time":53.43109812},
{"learn":[14.29977721],"iteration":55,"passed_time":3.160933316,"remaining_time":53.28430447},
{"learn":[14.24302644],"iteration":56,"passed_time":3.213371606,"remaining_time":53.16156886},
{"learn":[14.18285939],"iteration":57,"passed_time":3.265697229,"remaining_time":53.03942741},
{"learn":[14.13620433],"iteration":58,"passed_time":3.315409748,"remaining_time":52.87797581},
{"learn":[14.07903279],"iteration":59,"passed_time":3.366328711,"remaining_time":52.73914981},
{"learn":[14.03096948],"iteration":60,"passed_time":3.414599145,"remaining_time":52.56243602},
{"learn":[13.99630914],"iteration":61,"passed_time":3.464256193,"remaining_time":52.4108437},
{"learn":[13.94145466],"iteration":62,"passed_time":3.513957354,"remaining_time":52.26314351},
{"learn":[13.89645202],"iteration":63,"passed_time":3.56262888,"remaining_time":52.10344738},
{"learn":[13.8534345],"iteration":64,"passed_time":3.612925533,"remaining_time":51.97054421},
{"learn":[13.81770873],"iteration":65,"passed_time":3.663497253,"remaining_time":51.84403688},
{"learn":[13.77258004],"iteration":66,"passed_time":3.716958002,"remaining_time":51.7600271},
{"learn":[13.73476951],"iteration":67,"passed_time":3.768842713,"remaining_time":51.65531483},
{"learn":[13.7076325],"iteration":68,"passed_time":3.822538947,"remaining_time":51.57657622},
{"learn":[13.65867656],"iteration":69,"passed_time":3.883590102,"remaining_time":51.5962685},
{"learn":[13.62218428],"iteration":70,"passed_time":3.945221742,"remaining_time":51.62128167},
{"learn":[13.58765255],"iteration":71,"passed_time":3.999265472,"remaining_time":51.5460883},
{"learn":[13.55433929],"iteration":72,"passed_time":4.055705606,"remaining_time":51.50190544},
{"learn":[13.51654338],"iteration":73,"passed_time":4.116093727,"remaining_time":51.50679447},
{"learn":[13.47838867],"iteration":74,"passed_time":4.174871947,"remaining_time":51.49008734},
{"learn":[13.44962862],"iteration":75,"passed_time":4.230907886,"remaining_time":51.43893272},
{"learn":[13.40668543],"iteration":76,"passed_time":4.284071457,"remaining_time":51.35322019},
{"learn":[13.36220034],"iteration":77,"passed_time":4.335625939,"remaining_time":51.24932199},
{"learn":[13.33261068],"iteration":78,"passed_time":4.385945159,"remaining_time":51.13234799},
{"learn":[13.28826345],"iteration":79,"passed_time":4.440486182,"remaining_time":51.0655911},
{"learn":[13.25638122],"iteration":80,"passed_time":4.491788907,"remaining_time":50.96239513},
{"learn":[13.21662675],"iteration":81,"passed_time":4.543557413,"remaining_time":50.86567933},
{"learn":[13.18406759],"iteration":82,"passed_time":4.595367769,"remaining_time":50.77050896},
{"learn":[13.15944697],"iteration":83,"passed_time":4.649742523,"remaining_time":50.70433514},
{"learn":[13.12926653],"iteration":84,"passed_time":4.701418628,"remaining_time":50.60938876},
{"learn":[13.1025814],"iteration":85,"passed_time":4.754782362,"remaining_time":50.53338464},
{"learn":[13.06671265],"iteration":86,"passed_time":4.808610442,"remaining_time":50.46277395},
{"learn":[13.03242491],"iteration":87,"passed_time":4.859580872,"remaining_time":50.36292904},
{"learn":[13.00752883],"iteration":88,"passed_time":4.910517811,"remaining_time":50.26383961},
{"learn":[12.96767313],"iteration":89,"passed_time":4.962236314,"remaining_time":50.17372273},
{"learn":[12.94293439],"iteration":90,"passed_time":5.017072871,"remaining_time":50.11559604},
{"learn":[12.91809316],"iteration":91,"passed_time":5.069731376,"remaining_time":50.03604445},
{"learn":[12.89120024],"iteration":92,"passed_time":5.121471464,"remaining_time":49.94811417},
{"learn":[12.86345685],"iteration":93,"passed_time":5.172707413,"remaining_time":49.85609485},
{"learn":[12.84230226],"iteration":94,"passed_time":5.224214968,"remaining_time":49.76752153},
{"learn":[12.82099124],"iteration":95,"passed_time":5.275939694,"remaining_time":49.68176545},
{"learn":[12.79878044],"iteration":96,"passed_time":5.326413205,"remaining_time":49.58506313},
{"learn":[12.77448374],"iteration":97,"passed_time":5.374592425,"remaining_time":49.46818742},
{"learn":[12.74844968],"iteration":98,"passed_time":5.424717082,"remaining_time":49.37040496},
{"learn":[12.72837008],"iteration":99,"passed_time":5.473060843,"remaining_time":49.25754759},
{"learn":[12.71526977],"iteration":100,"passed_time":5.523336352,"remaining_time":49.16316218},
{"learn":[12.69175658],"iteration":101,"passed_time":5.576650638,"remaining_time":49.09639483},
{"learn":[12.67095694],"iteration":102,"passed_time":5.633051702,"remaining_time":49.05677065},
{"learn":[12.65019997],"iteration":103,"passed_time":5.6864461,"remaining_time":48.99092024},
{"learn":[12.629023],"iteration":104,"passed_time":5.740962083,"remaining_time":48.93486728},
{"learn":[12.61726746],"iteration":105,"passed_time":5.791647926,"remaining_time":48.84654005},
{"learn":[12.59889204],"iteration":106,"passed_time":5.841451892,"remaining_time":48.75155644},
{"learn":[12.57792274],"iteration":107,"passed_time":5.889712742,"remaining_time":48.6446645},
{"learn":[12.5606968],"iteration":108,"passed_time":5.938035698,"remaining_time":48.53935603},
{"learn":[12.53312662],"iteration":109,"passed_time":5.986275246,"remaining_time":48.43440881},
{"learn":[12.51189626],"iteration":110,"passed_time":6.041016528,"remaining_time":48.3825558},
{"learn":[12.48389026],"iteration":111,"passed_time":6.092077234,"remaining_time":48.3014695},
{"learn":[12.46784074],"iteration":112,"passed_time":6.144127626,"remaining_time":48.22868323},
{"learn":[12.44581593],"iteration":113,"passed_time":6.199905389,"remaining_time":48.18522961},
{"learn":[12.4170635],"iteration":114,"passed_time":6.256122787,"remaining_time":48.14494493},
{"learn":[12.38979007],"iteration":115,"passed_time":6.311360382,"remaining_time":48.09691877},
{"learn":[12.36971566],"iteration":116,"passed_time":6.361245469,"remaining_time":48.00837392},
{"learn":[12.34626257],"iteration":117,"passed_time":6.411411097,"remaining_time":47.92258125},
{"learn":[12.32633063],"iteration":118,"passed_time":6.459923583,"remaining_time":47.82514854},
{"learn":[12.31013862],"iteration":119,"passed_time":6.509207656,"remaining_time":47.73418948},
{"learn":[12.2907817],"iteration":120,"passed_time":6.558704755,"remaining_time":47.64546678},
{"learn":[12.27309505],"iteration":121,"passed_time":6.609205867,"remaining_time":47.56461271},
{"learn":[12.25428071],"iteration":122,"passed_time":6.66021026,"remaining_time":47.48784064},
{"learn":[12.23035175],"iteration":123,"passed_time":6.710821468,"remaining_time":47.4087065},
{"learn":[12.21888014],"iteration":124,"passed_time":6.760841037,"remaining_time":47.32588726},
{"learn":[12.19163468],"iteration":125,"passed_time":6.811528395,"remaining_time":47.24822077},
{"learn":[12.18184098],"iteration":126,"passed_time":6.863156441,"remaining_time":47.17744546},
{"learn":[12.16222297],"iteration":127,"passed_time":6.91421487,"remaining_time":47.1030888},
{"learn":[12.14576206],"iteration":128,"passed_time":6.965571494,"remaining_time":47.03110676},
{"learn":[12.12818113],"iteration":129,"passed_time":7.017735491,"remaining_time":46.96484521},
{"learn":[12.10953337],"iteration":130,"passed_time":7.068210982,"remaining_time":46.88759804},
{"learn":[12.09126055],"iteration":131,"passed_time":7.126427336,"remaining_time":46.86165854},
{"learn":[12.07557646],"iteration":132,"passed_time":7.184810452,"remaining_time":46.83632077},
{"learn":[12.06308514],"iteration":133,"passed_time":7.236104396,"remaining_time":46.76467468},
{"learn":[12.05122465],"iteration":134,"passed_time":7.287089869,"remaining_time":46.6913536},
{"learn":[12.03362111],"iteration":135,"passed_time":7.336783877,"remaining_time":46.61015639},
{"learn":[12.01625804],"iteration":136,"passed_time":7.386709765,"remaining_time":46.53087976},
{"learn":[11.99980067],"iteration":137,"passed_time":7.437797797,"remaining_time":46.45928769},
{"learn":[11.98779807],"iteration":138,"passed_time":7.489363432,"remaining_time":46.39094903},
{"learn":[11.9709228],"iteration":139,"passed_time":7.541115197,"remaining_time":46.32399336},
{"learn":[11.95608934],"iteration":140,"passed_time":7.591180829,"remaining_time":46.24698108},
{"learn":[11.94104838],"iteration":141,"passed_time":7.640492477,"remaining_time":46.16579257},
{"learn":[11.93019335],"iteration":142,"passed_time":7.687403592,"remaining_time":46.07066348},
{"learn":[11.91778787],"iteration":143,"passed_time":7.737620781,"remaining_time":45.99585686},
{"learn":[11.90463629],"iteration":144,"passed_time":7.786833189,"remaining_time":45.91546467},
{"learn":[11.88793133],"iteration":145,"passed_time":7.841460374,"remaining_time":45.86717232},
{"learn":[11.87387157],"iteration":146,"passed_time":7.889496164,"remaining_time":45.78054577},
{"learn":[11.86177869],"iteration":147,"passed_time":7.937790999,"remaining_time":45.69593197},
{"learn":[11.84839438],"iteration":148,"passed_time":7.986406082,"remaining_time":45.61363474},
{"learn":[11.83433321],"iteration":149,"passed_time":8.038839708,"remaining_time":45.55342501},
{"learn":[11.82098006],"iteration":150,"passed_time":8.093429989,"remaining_time":45.50544411},
{"learn":[11.80338006],"iteration":151,"passed_time":8.143850256,"remaining_time":45.43411195},
{"learn":[11.78383404],"iteration":152,"passed_time":8.200159276,"remaining_time":45.39565299},
{"learn":[11.77071839],"iteration":153,"passed_time":8.252449898,"remaining_time":45.3348871},
{"learn":[11.75823462],"iteration":154,"passed_time":8.303751709,"remaining_time":45.26883996},
{"learn":[11.74390379],"iteration":155,"passed_time":8.353571428,"remaining_time":45.19496337},
{"learn":[11.72893438],"iteration":156,"passed_time":8.404914748,"remaining_time":45.12957409},
{"learn":[11.71181091],"iteration":157,"passed_time":8.455315885,"remaining_time":45.05934161},
{"learn":[11.69782585],"iteration":158,"passed_time":8.50662841,"remaining_time":44.9941792},
{"learn":[11.68661456],"iteration":159,"passed_time":8.556565939,"remaining_time":44.92197118},
{"learn":[11.67184546],"iteration":160,"passed_time":8.608389124,"remaining_time":44.8598663},
{"learn":[11.65505396],"iteration":161,"passed_time":8.660975534,"remaining_time":44.8018364},
{"learn":[11.63857727],"iteration":162,"passed_time":8.713799158,"remaining_time":44.74509138},
{"learn":[11.62475655],"iteration":163,"passed_time":8.765204853,"remaining_time":44.6811662},
{"learn":[11.60320583],"iteration":164,"passed_time":8.816974327,"remaining_time":44.61923372},
{"learn":[11.58833555],"iteration":165,"passed_time":8.868313595,"remaining_time":44.55526228},
{"learn":[11.5738514],"iteration":166,"passed_time":8.91886383,"remaining_time":44.48750641},
{"learn":[11.56038707],"iteration":167,"passed_time":8.970211282,"remaining_time":44.42390349},
{"learn":[11.54440683],"iteration":168,"passed_time":9.020616912,"remaining_time":44.35581452},
{"learn":[11.53095482],"iteration":169,"passed_time":9.071684312,"remaining_time":44.29116458},
{"learn":[11.51827241],"iteration":170,"passed_time":9.123042188,"remaining_time":44.22808172},
{"learn":[11.50650829],"iteration":171,"passed_time":9.173718219,"remaining_time":44.16185282},
{"learn":[11.49370146],"iteration":172,"passed_time":9.223535768,"remaining_time":44.09169989},
{"learn":[11.47932751],"iteration":173,"passed_time":9.274613275,"remaining_time":44.02776187},
{"learn":[11.4649986],"iteration":174,"passed_time":9.32450811,"remaining_time":43.95839537},
{"learn":[11.44829549],"iteration":175,"passed_time":9.374612084,"remaining_time":43.8902293},
{"learn":[11.43088231],"iteration":176,"passed_time":9.424803168,"remaining_time":43.82267236},
{"learn":[11.41878089],"iteration":177,"passed_time":9.47538807,"remaining_time":43.75712918},
{"learn":[11.39997873],"iteration":178,"passed_time":9.528132669,"remaining_time":43.70165878},
{"learn":[11.38631259],"iteration":179,"passed_time":9.579682479,"remaining_time":43.64077574},
{"learn":[11.36985563],"iteration":180,"passed_time":9.630139144,"remaining_time":43.5750495},
{"learn":[11.35239041],"iteration":181,"passed_time":9.682677303,"remaining_time":43.51884634},
{"learn":[11.34111182],"iteration":182,"passed_time":9.736210667,"remaining_time":43.46712631},
{"learn":[11.33007903],"iteration":183,"passed_time":9.78790475,"remaining_time":43.40722976},
{"learn":[11.32078269],"iteration":184,"passed_time":9.837975667,"remaining_time":43.34027118},
{"learn":[11.31030095],"iteration":185,"passed_time":9.88820179,"remaining_time":43.27417343},
{"learn":[11.29607565],"iteration":186,"passed_time":9.939355182,"remaining_time":43.21227681},
{"learn":[11.28423099],"iteration":187,"passed_time":9.992175178,"remaining_time":43.15769279},
{"learn":[11.27207612],"iteration":188,"passed_time":10.04310827,"remaining_time":43.09503071},
{"learn":[11.25868583],"iteration":189,"passed_time":10.09389948,"remaining_time":43.03188727},
{"learn":[11.24833628],"iteration":190,"passed_time":10.14459345,"remaining_time":42.96846125},
{"learn":[11.23246414],"iteration":191,"passed_time":10.19670462,"remaining_time":42.91113193},
{"learn":[11.21948812],"iteration":192,"passed_time":10.24949899,"remaining_time":42.85671341},
{"learn":[11.21000911],"iteration":193,"passed_time":10.30067894,"remaining_time":42.79560425},
{"learn":[11.19636494],"iteration":194,"passed_time":10.35274744,"remaining_time":42.73826506},
{"learn":[11.1811338],"iteration":195,"passed_time":10.40137449,"remaining_time":42.66686271},
{"learn":[11.16666507],"iteration":196,"passed_time":10.44992112,"remaining_time":42.59536375},
{"learn":[11.15088297],"iteration":197,"passed_time":10.49866452,"remaining_time":42.52489365},
{"learn":[11.14104439],"iteration":198,"passed_time":10.5505288,"remaining_time":42.46720385},
{"learn":[11.12978004],"iteration":199,"passed_time":10.59911403,"remaining_time":42.39645612},
{"learn":[11.11833048],"iteration":200,"passed_time":10.64864804,"remaining_time":42.32970043},
{"learn":[11.10283328],"iteration":201,"passed_time":10.69830015,"remaining_time":42.26358177},
{"learn":[11.08507653],"iteration":202,"passed_time":10.74806767,"remaining_time":42.19807848},
{"learn":[11.0734295],"iteration":203,"passed_time":10.80022774,"remaining_time":42.1420651},
{"learn":[11.06040561],"iteration":204,"passed_time":10.84868016,"remaining_time":42.07171087},
{"learn":[11.04630939],"iteration":205,"passed_time":10.89834325,"remaining_time":42.00623563},
{"learn":[11.02943055],"iteration":206,"passed_time":10.94763008,"remaining_time":41.93947177},
{"learn":[11.01796786],"iteration":207,"passed_time":10.99951892,"remaining_time":41.88278359},
{"learn":[11.00851753],"iteration":208,"passed_time":11.05316975,"remaining_time":41.8328099},
{"learn":[10.99792915],"iteration":209,"passed_time":11.1052396,"remaining_time":41.77685372},
{"learn":[10.98427196],"iteration":210,"passed_time":11.15628772,"remaining_time":41.7171138},
{"learn":[10.96711467],"iteration":211,"passed_time":11.20746397,"remaining_time":41.65793211},
{"learn":[10.95262804],"iteration":212,"passed_time":11.25998212,"remaining_time":41.60378369},
{"learn":[10.9416506],"iteration":213,"passed_time":11.31338589,"remaining_time":41.55290332},
{"learn":[10.93241495],"iteration":214,"passed_time":11.36492662,"remaining_time":41.49519719},
{"learn":[10.92148787],"iteration":215,"passed_time":11.41710044,"remaining_time":41.43984605},
{"learn":[10.91185571],"iteration":216,"passed_time":11.46603921,"remaining_time":41.37285116},
{"learn":[10.90199557],"iteration":217,"passed_time":11.51650505,"remaining_time":41.31149977},
{"learn":[10.89001231],"iteration":218,"passed_time":11.56842375,"remaining_time":41.255429},
{"learn":[10.8815942],"iteration":219,"passed_time":11.61809931,"remaining_time":41.19144299},
{"learn":[10.8707681],"iteration":220,"passed_time":11.66693092,"remaining_time":41.12461172},
{"learn":[10.86169178],"iteration":221,"passed_time":11.71722464,"remaining_time":41.06306652},
{"learn":[10.84997856],"iteration":222,"passed_time":11.76690064,"remaining_time":40.99946993},
{"learn":[10.83794767],"iteration":223,"passed_time":11.81895156,"remaining_time":40.94422503},
{"learn":[10.83144656],"iteration":224,"passed_time":11.86949957,"remaining_time":40.88383187},
{"learn":[10.82533785],"iteration":225,"passed_time":11.91980629,"remaining_time":40.8226994},
{"learn":[10.81249988],"iteration":226,"passed_time":11.97005934,"remaining_time":40.76147959},
{"learn":[10.79871063],"iteration":227,"passed_time":12.01967648,"remaining_time":40.69820281},
{"learn":[10.7897053],"iteration":228,"passed_time":12.07359242,"remaining_time":40.6495186},
{"learn":[10.77852133],"iteration":229,"passed_time":12.14028833,"remaining_time":40.64357398},
{"learn":[10.77209327],"iteration":230,"passed_time":12.19421432,"remaining_time":40.59459227},
{"learn":[10.76249904],"iteration":231,"passed_time":12.24590658,"remaining_time":40.53817352},
{"learn":[10.75164912],"iteration":232,"passed_time":12.29630962,"remaining_time":40.4775514},
{"learn":[10.74063217],"iteration":233,"passed_time":12.3478478,"remaining_time":40.42073254},
{"learn":[10.73298663],"iteration":234,"passed_time":12.39731926,"remaining_time":40.35723078},
{"learn":[10.72702174],"iteration":235,"passed_time":12.44741261,"remaining_time":40.29586117},
{"learn":[10.71441295],"iteration":236,"passed_time":12.49745463,"remaining_time":40.23442146},
{"learn":[10.70552858],"iteration":237,"passed_time":12.54644649,"remaining_time":40.16971524},
{"learn":[10.69281017],"iteration":238,"passed_time":12.59565821,"remaining_time":40.10584059},
{"learn":[10.68899924],"iteration":239,"passed_time":12.64483574,"remaining_time":40.04197984},
{"learn":[10.6804417],"iteration":240,"passed_time":12.69439393,"remaining_time":39.9794398},
{"learn":[10.67177568],"iteration":241,"passed_time":12.74362828,"remaining_time":39.9159927},
{"learn":[10.66482922],"iteration":242,"passed_time":12.79274231,"remaining_time":39.85228777},
{"learn":[10.65515271],"iteration":243,"passed_time":12.84182624,"remaining_time":39.78860917},
{"learn":[10.65164317],"iteration":244,"passed_time":12.891404,"remaining_time":39.7265715},
{"learn":[10.6426163],"iteration":245,"passed_time":12.94377676,"remaining_time":39.67320195},
{"learn":[10.63155908],"iteration":246,"passed_time":12.99823684,"remaining_time":39.62620382},
{"learn":[10.62076377],"iteration":247,"passed_time":13.05276025,"remaining_time":39.57933754},
{"learn":[10.60799151],"iteration":248,"passed_time":13.10240522,"remaining_time":39.51769608},
{"learn":[10.59841593],"iteration":249,"passed_time":13.15298017,"remaining_time":39.4589405},
{"learn":[10.58652473],"iteration":250,"passed_time":13.20110859,"remaining_time":39.39294952},
{"learn":[10.5761526],"iteration":251,"passed_time":13.25045751,"remaining_time":39.33072309},
{"learn":[10.56965198],"iteration":252,"passed_time":13.3002695,"remaining_time":39.26996569},
{"learn":[10.55712794],"iteration":253,"passed_time":13.3516383,"remaining_time":39.21386681},
{"learn":[10.54965954],"iteration":254,"passed_time":13.40185872,"remaining_time":39.15444999},
{"learn":[10.53977077],"iteration":255,"passed_time":13.45189042,"remaining_time":39.09455652},
{"learn":[10.53196162],"iteration":256,"passed_time":13.5031535,"remaining_time":39.0382998},
{"learn":[10.52540466],"iteration":257,"passed_time":13.55430656,"remaining_time":38.98176538},
{"learn":[10.51589895],"iteration":258,"passed_time":13.60464095,"remaining_time":38.92293028},
{"learn":[10.51101174],"iteration":259,"passed_time":13.65394017,"remaining_time":38.86121434},
{"learn":[10.50054841],"iteration":260,"passed_time":13.70493207,"remaining_time":38.80438621},
{"learn":[10.49620286],"iteration":261,"passed_time":13.75491468,"remaining_time":38.74475968},
{"learn":[10.48840652],"iteration":262,"passed_time":13.80589239,"remaining_time":38.68799503},
{"learn":[10.47913744],"iteration":263,"passed_time":13.85670384,"remaining_time":38.63081071},
{"learn":[10.46996487],"iteration":264,"passed_time":13.90859705,"remaining_time":38.57667484},
{"learn":[10.46367542],"iteration":265,"passed_time":13.95971833,"remaining_time":38.52042576},
{"learn":[10.45517513],"iteration":266,"passed_time":14.00939625,"remaining_time":38.46025262},
{"learn":[10.44999584],"iteration":267,"passed_time":14.06198848,"remaining_time":38.40811778},
{"learn":[10.44312297],"iteration":268,"passed_time":14.11344177,"remaining_time":38.3528845},
{"learn":[10.43450703],"iteration":269,"passed_time":14.16329263,"remaining_time":38.29334673},
{"learn":[10.42650397],"iteration":270,"passed_time":14.21234724,"remaining_time":38.23173853},
{"learn":[10.41777175],"iteration":271,"passed_time":14.2617686,"remaining_time":38.17120418},
{"learn":[10.40550463],"iteration":272,"passed_time":14.31075843,"remaining_time":38.10960211},
{"learn":[10.39270344],"iteration":273,"passed_time":14.36737903,"remaining_time":38.06831086},
{"learn":[10.38301034],"iteration":274,"passed_time":14.42150849,"remaining_time":38.02034057},
{"learn":[10.37366064],"iteration":275,"passed_time":14.47467933,"remaining_time":37.969811},
{"learn":[10.36977977],"iteration":276,"passed_time":14.52282054,"remaining_time":37.90613448},
{"learn":[10.366472],"iteration":277,"passed_time":14.57055676,"remaining_time":37.84151793},
{"learn":[10.35576814],"iteration":278,"passed_time":14.62014363,"remaining_time":37.78180486},
{"learn":[10.34498927],"iteration":279,"passed_time":14.67012087,"remaining_time":37.72316795},
{"learn":[10.33623309],"iteration":280,"passed_time":14.71974233,"remaining_time":37.66368232},
{"learn":[10.33015033],"iteration":281,"passed_time":14.76798589,"remaining_time":37.6007584},
{"learn":[10.32477121],"iteration":282,"passed_time":14.81676208,"remaining_time":37.53928766},
{"learn":[10.31408037],"iteration":283,"passed_time":14.86557176,"remaining_time":37.47799077},
{"learn":[10.30492295],"iteration":284,"passed_time":14.9168906,"remaining_time":37.42307641},
{"learn":[10.29896834],"iteration":285,"passed_time":14.9710922,"remaining_time":37.37538402},
{"learn":[10.29114601],"iteration":286,"passed_time":15.02832948,"remaining_time":37.33518787},
{"learn":[10.28819901],"iteration":287,"passed_time":15.08205034,"remaining_time":37.28618},
{"learn":[10.27982251],"iteration":288,"passed_time":15.13721525,"remaining_time":37.2406922},
{"learn":[10.27157542],"iteration":289,"passed_time":15.1941866,"remaining_time":37.1995603},
{"learn":[10.26496625],"iteration":290,"passed_time":15.25279909,"remaining_time":37.16231807},
{"learn":[10.25736637],"iteration":291,"passed_time":15.31097059,"remaining_time":37.1238602},
{"learn":[10.25253846],"iteration":292,"passed_time":15.36573305,"remaining_time":37.07704187},
{"learn":[10.24799101],"iteration":293,"passed_time":15.41759411,"remaining_time":37.02320219},
{"learn":[10.23777429],"iteration":294,"passed_time":15.47181334,"remaining_time":36.97501155},
{"learn":[10.22807817],"iteration":295,"passed_time":15.52481188,"remaining_time":36.9238769},
{"learn":[10.2211771],"iteration":296,"passed_time":15.57668688,"remaining_time":36.8700703},
{"learn":[10.21332942],"iteration":297,"passed_time":15.6311251,"remaining_time":36.82231484},
{"learn":[10.20187701],"iteration":298,"passed_time":15.68545979,"remaining_time":36.77427194},
{"learn":[10.19885813],"iteration":299,"passed_time":15.74158454,"remaining_time":36.73036394},
{"learn":[10.19118191],"iteration":300,"passed_time":15.79826718,"remaining_time":36.68767031},
{"learn":[10.18401429],"iteration":301,"passed_time":15.84756142,"remaining_time":36.62780752},
{"learn":[10.18098195],"iteration":302,"passed_time":15.89749948,"remaining_time":36.5694955},
{"learn":[10.17383638],"iteration":303,"passed_time":15.94780019,"remaining_time":36.51206886},
{"learn":[10.16523254],"iteration":304,"passed_time":15.99717867,"remaining_time":36.45258747},
{"learn":[10.15612874],"iteration":305,"passed_time":16.04878688,"remaining_time":36.39822906},
{"learn":[10.15163409],"iteration":306,"passed_time":16.10466025,"remaining_time":36.35351646},
{"learn":[10.13961294],"iteration":307,"passed_time":16.1609501,"remaining_time":36.3096671},
{"learn":[10.1334651],"iteration":308,"passed_time":16.21419596,"remaining_time":36.25893013},
{"learn":[10.12605308],"iteration":309,"passed_time":16.27270202,"remaining_time":36.21988514},
{"learn":[10.11792311],"iteration":310,"passed_time":16.32434699,"remaining_time":36.16551472},
{"learn":[10.11400413],"iteration":311,"passed_time":16.37361959,"remaining_time":36.10593038},
{"learn":[10.10671172],"iteration":312,"passed_time":16.42192986,"remaining_time":36.04429973},
{"learn":[10.09849456],"iteration":313,"passed_time":16.47177216,"remaining_time":35.98610096},
{"learn":[10.09085851],"iteration":314,"passed_time":16.51967681,"remaining_time":35.92374163},
{"learn":[10.08345296],"iteration":315,"passed_time":16.57032394,"remaining_time":35.86741004},
{"learn":[10.07927314],"iteration":316,"passed_time":16.62091996,"remaining_time":35.8110042},
{"learn":[10.07108812],"iteration":317,"passed_time":16.6725191,"remaining_time":35.75678625},
{"learn":[10.06704514],"iteration":318,"passed_time":16.72045895,"remaining_time":35.69477288},
{"learn":[10.05940684],"iteration":319,"passed_time":16.77003909,"remaining_time":35.63633306},
{"learn":[10.05177791],"iteration":320,"passed_time":16.81901798,"remaining_time":35.57667665},
{"learn":[10.0472897],"iteration":321,"passed_time":16.86765714,"remaining_time":35.51637125},
{"learn":[10.03938373],"iteration":322,"passed_time":16.91746199,"remaining_time":35.45858133},
{"learn":[10.03045961],"iteration":323,"passed_time":16.97214004,"remaining_time":35.41100824},
{"learn":[10.02215869],"iteration":324,"passed_time":17.02951584,"remaining_time":35.36899444},
{"learn":[10.0104526],"iteration":325,"passed_time":17.07714925,"remaining_time":35.30674416},
{"learn":[10.00495759],"iteration":326,"passed_time":17.12575727,"remaining_time":35.24658912},
{"learn":[9.994415249],"iteration":327,"passed_time":17.17515137,"remaining_time":35.188115},
{"learn":[9.989828318],"iteration":328,"passed_time":17.22332491,"remaining_time":35.12720672},
{"learn":[9.981742545],"iteration":329,"passed_time":17.27270538,"remaining_time":35.06882608},
{"learn":[9.976700556],"iteration":330,"passed_time":17.3238777,"remaining_time":35.01412139},
{"learn":[9.969505697],"iteration":331,"passed_time":17.37851151,"remaining_time":34.96640268},
{"learn":[9.960121356],"iteration":332,"passed_time":17.44257795,"remaining_time":34.93753601},
{"learn":[9.954125282],"iteration":333,"passed_time":17.51673339,"remaining_time":34.92857617},
{"learn":[9.945151336],"iteration":334,"passed_time":17.57574784,"remaining_time":34.88917109},
{"learn":[9.937232828],"iteration":335,"passed_time":17.62806129,"remaining_time":34.83640684},
{"learn":[9.931015945],"iteration":336,"passed_time":17.67698137,"remaining_time":34.77696927},
{"learn":[9.924446475],"iteration":337,"passed_time":17.72525262,"remaining_time":34.71632317},
{"learn":[9.918794246],"iteration":338,"passed_time":17.77314545,"remaining_time":34.65501222},
{"learn":[9.908153835],"iteration":339,"passed_time":17.8218285,"remaining_time":34.59531415},
{"learn":[9.900801252],"iteration":340,"passed_time":17.87086387,"remaining_time":34.53636156},
{"learn":[9.892097339],"iteration":341,"passed_time":17.9193975,"remaining_time":34.47650162},
{"learn":[9.886853227],"iteration":342,"passed_time":17.96801913,"remaining_time":34.4168763},
{"learn":[9.875576045],"iteration":343,"passed_time":18.01648827,"remaining_time":34.35702414},
{"learn":[9.871077239],"iteration":344,"passed_time":18.06562623,"remaining_time":34.29850777},
{"learn":[9.866069026],"iteration":345,"passed_time":18.1148865,"remaining_time":34.24027679},
{"learn":[9.858758781],"iteration":346,"passed_time":18.17061156,"remaining_time":34.19426326},
{"learn":[9.85314261],"iteration":347,"passed_time":18.2187912,"remaining_time":34.13405707},
{"learn":[9.846797838],"iteration":348,"passed_time":18.26739668,"remaining_time":34.07471415},
{"learn":[9.841523802],"iteration":349,"passed_time":18.31603343,"remaining_time":34.01549066},
{"learn":[9.834727239],"iteration":350,"passed_time":18.36525815,"remaining_time":33.95741464},
{"learn":[9.831239869],"iteration":351,"passed_time":18.41428178,"remaining_time":33.89901873},
{"learn":[9.825405979],"iteration":352,"passed_time":18.46449221,"remaining_time":33.84285116},
{"learn":[9.819239708],"iteration":353,"passed_time":18.51275343,"remaining_time":33.78316021},
{"learn":[9.815231515],"iteration":354,"passed_time":18.56152873,"remaining_time":33.72446769},
{"learn":[9.808178031],"iteration":355,"passed_time":18.61124964,"remaining_time":33.66754148},
{"learn":[9.802276697],"iteration":356,"passed_time":18.66002699,"remaining_time":33.60895618},
{"learn":[9.798750833],"iteration":357,"passed_time":18.71196585,"remaining_time":33.55609518},
{"learn":[9.791893109],"iteration":358,"passed_time":18.76025663,"remaining_time":33.49672562},
{"learn":[9.785260651],"iteration":359,"passed_time":18.80895752,"remaining_time":33.4381467},
{"learn":[9.776024141],"iteration":360,"passed_time":18.85803141,"remaining_time":33.38028274},
{"learn":[9.767487194],"iteration":361,"passed_time":18.90800692,"remaining_time":33.32405639},
{"learn":[9.76490071],"iteration":362,"passed_time":18.95861681,"remaining_time":33.26897771},
{"learn":[9.757139213],"iteration":363,"passed_time":19.00702938,"remaining_time":33.21008431},
{"learn":[9.748623466],"iteration":364,"passed_time":19.05603552,"remaining_time":33.15228096},
{"learn":[9.744407679],"iteration":365,"passed_time":19.10369975,"remaining_time":33.0922012},
{"learn":[9.738777521],"iteration":366,"passed_time":19.1532882,"remaining_time":33.03550798},
{"learn":[9.734200691],"iteration":367,"passed_time":19.20149302,"remaining_time":32.97647714},
{"learn":[9.728981227],"iteration":368,"passed_time":19.24986219,"remaining_time":32.91778601},
{"learn":[9.72501972],"iteration":369,"passed_time":19.29837355,"remaining_time":32.85939279},
{"learn":[9.718377862],"iteration":370,"passed_time":19.3471591,"remaining_time":32.80151772},
{"learn":[9.708908745],"iteration":371,"passed_time":19.39639696,"remaining_time":32.74445508},
{"learn":[9.705734173],"iteration":372,"passed_time":19.44594924,"remaining_time":32.68796293},
{"learn":[9.701870721],"iteration":373,"passed_time":19.49488612,"remaining_time":32.63047784},
{"learn":[9.697139152],"iteration":374,"passed_time":19.54270522,"remaining_time":32.57117537},
{"learn":[9.690511002],"iteration":375,"passed_time":19.59198616,"remaining_time":32.51436002},
{"learn":[9.685140463],"iteration":376,"passed_time":19.63912173,"remaining_time":32.45403937},
{"learn":[9.681963062],"iteration":377,"passed_time":19.6874807,"remaining_time":32.39580157},
{"learn":[9.675044046],"iteration":378,"passed_time":19.73606873,"remaining_time":32.33799125},
{"learn":[9.6687722],"iteration":379,"passed_time":19.78475674,"remaining_time":32.28039257},
{"learn":[9.660027792],"iteration":380,"passed_time":19.83405365,"remaining_time":32.22382995},
{"learn":[9.650534961],"iteration":381,"passed_time":19.88306507,"remaining_time":32.16684349},
{"learn":[9.646634528],"iteration":382,"passed_time":19.93301375,"remaining_time":32.11140857},
{"learn":[9.644341211],"iteration":383,"passed_time":19.98041488,"remaining_time":32.05191554},
{"learn":[9.638772889],"iteration":384,"passed_time":20.02858892,"remaining_time":31.99371996},
{"learn":[9.636304609],"iteration":385,"passed_time":20.07778382,"remaining_time":31.93720017},
{"learn":[9.631370875],"iteration":386,"passed_time":20.12843568,"remaining_time":31.88302602},
{"learn":[9.624282686],"iteration":387,"passed_time":20.17807029,"remaining_time":31.82726551},
{"learn":[9.622234754],"iteration":388,"passed_time":20.22888041,"remaining_time":31.77338286},
{"learn":[9.618111032],"iteration":389,"passed_time":20.28266872,"remaining_time":31.72417415},
{"learn":[9.613244469],"iteration":390,"passed_time":20.33595706,"remaining_time":31.67416329},
{"learn":[9.605964194],"iteration":391,"passed_time":20.39378357,"remaining_time":31.63117452},
{"learn":[9.601676038],"iteration":392,"passed_time":20.4561572,"remaining_time":31.59513338},
{"learn":[9.593241492],"iteration":393,"passed_time":20.52327543,"remaining_time":31.56625611},
{"learn":[9.58689229],"iteration":394,"passed_time":20.58523243,"remaining_time":31.52928005},
{"learn":[9.583400652],"iteration":395,"passed_time":20.64765965,"remaining_time":31.49289502},
{"learn":[9.576475118],"iteration":396,"passed_time":20.70941175,"remaining_time":31.45535337},
{"learn":[9.569698923],"iteration":397,"passed_time":20.7634385,"remaining_time":31.40600496},
{"learn":[9.565007252],"iteration":398,"passed_time":20.81491228,"remaining_time":31.35278767},
{"learn":[9.559423403],"iteration":399,"passed_time":20.86396912,"remaining_time":31.29595369},
{"learn":[9.553340882],"iteration":400,"passed_time":20.91209567,"remaining_time":31.23776885},
{"learn":[9.547197237],"iteration":401,"passed_time":20.96098113,"remaining_time":31.18076298},
{"learn":[9.539879196],"iteration":402,"passed_time":21.00962536,"remaining_time":31.12344005},
{"learn":[9.535333101],"iteration":403,"passed_time":21.05849891,"remaining_time":31.0664984},
{"learn":[9.529815427],"iteration":404,"passed_time":21.10701251,"remaining_time":31.00906777},
{"learn":[9.522890025],"iteration":405,"passed_time":21.15749086,"remaining_time":30.9545556},
{"learn":[9.519299166],"iteration":406,"passed_time":21.20759321,"remaining_time":30.89951542},
{"learn":[9.515096846],"iteration":407,"passed_time":21.26242766,"remaining_time":30.85136562},
{"learn":[9.50999248],"iteration":408,"passed_time":21.32434183,"remaining_time":30.81341325},
{"learn":[9.502609197],"iteration":409,"passed_time":21.38389824,"remaining_time":30.77195113},
{"learn":[9.498657329],"iteration":410,"passed_time":21.44175234,"remaining_time":30.72796139},
{"learn":[9.492767929],"iteration":411,"passed_time":21.49245132,"remaining_time":30.67369266},
{"learn":[9.487430584],"iteration":412,"passed_time":21.54116014,"remaining_time":30.6166126},
{"learn":[9.482837396],"iteration":413,"passed_time":21.58931722,"remaining_time":30.558792},
{"learn":[9.478985918],"iteration":414,"passed_time":21.63845839,"remaining_time":30.50240521},
{"learn":[9.475375691],"iteration":415,"passed_time":21.68737358,"remaining_time":30.44573599},
{"learn":[9.471449337],"iteration":416,"passed_time":21.73540398,"remaining_time":30.38786696},
{"learn":[9.465011299],"iteration":417,"passed_time":21.78391938,"remaining_time":30.33072028},
{"learn":[9.458810394],"iteration":418,"passed_time":21.83463114,"remaining_time":30.27666036},
{"learn":[9.450584984],"iteration":419,"passed_time":21.8852707,"remaining_time":30.22251669},
{"learn":[9.446025853],"iteration":420,"passed_time":21.94304931,"remaining_time":30.17820796},
{"learn":[9.441039543],"iteration":421,"passed_time":22.00159169,"remaining_time":30.1348815},
{"learn":[9.437762247],"iteration":422,"passed_time":22.05607949,"remaining_time":30.08595241},
{"learn":[9.431094202],"iteration":423,"passed_time":22.11371424,"remaining_time":30.04127217},
{"learn":[9.427847336],"iteration":424,"passed_time":22.16973641,"remaining_time":29.99434926},
{"learn":[9.42485737],"iteration":425,"passed_time":22.22402254,"remaining_time":29.94504445},
{"learn":[9.418459271],"iteration":426,"passed_time":22.28196877,"remaining_time":29.90062788},
{"learn":[9.412609061],"iteration":427,"passed_time":22.33602759,"remaining_time":29.85095275},
{"learn":[9.408260702],"iteration":428,"passed_time":22.38804168,"remaining_time":29.79853566},
{"learn":[9.405108085],"iteration":429,"passed_time":22.43891697,"remaining_time":29.74461087},
{"learn":[9.400068248],"iteration":430,"passed_time":22.4891863,"remaining_time":29.68990024},
{"learn":[9.39138957],"iteration":431,"passed_time":22.53793432,"remaining_time":29.63320995},
{"learn":[9.38906839],"iteration":432,"passed_time":22.5870493,"remaining_time":29.57703685},
{"learn":[9.384050565],"iteration":433,"passed_time":22.64041181,"remaining_time":29.52643568},
{"learn":[9.377005583],"iteration":434,"passed_time":22.69246194,"remaining_time":29.47411723},
{"learn":[9.37130035],"iteration":435,"passed_time":22.74369684,"remaining_time":29.42074545},
{"learn":[9.368873187],"iteration":436,"passed_time":22.79250618,"remaining_time":29.36425854},
{"learn":[9.366517215],"iteration":437,"passed_time":22.8414782,"remaining_time":29.30801541},
{"learn":[9.361912506],"iteration":438,"passed_time":22.88978127,"remaining_time":29.25095055},
{"learn":[9.355956107],"iteration":439,"passed_time":22.94026022,"remaining_time":29.19669483},
{"learn":[9.348646791],"iteration":440,"passed_time":22.98820003,"remaining_time":29.13923768},
{"learn":[9.344036239],"iteration":441,"passed_time":23.03667994,"remaining_time":29.08250545},
{"learn":[9.341041553],"iteration":442,"passed_time":23.08476225,"remaining_time":29.02531054},
{"learn":[9.334594474],"iteration":443,"passed_time":23.133411,"remaining_time":28.96886603},
{"learn":[9.325638025],"iteration":444,"passed_time":23.18238638,"remaining_time":28.91286392},
{"learn":[9.321401052],"iteration":445,"passed_time":23.23122654,"remaining_time":28.85672534},
{"learn":[9.316603407],"iteration":446,"passed_time":23.27970212,"remaining_time":28.8001684},
{"learn":[9.310855689],"iteration":447,"passed_time":23.32813158,"remaining_time":28.7435907},
{"learn":[9.303749168],"iteration":448,"passed_time":23.37652403,"remaining_time":28.68700388},
{"learn":[9.29939658],"iteration":449,"passed_time":23.42544117,"remaining_time":28.63109477},
{"learn":[9.296606515],"iteration":450,"passed_time":23.47828266,"remaining_time":28.57999375},
{"learn":[9.293077289],"iteration":451,"passed_time":23.52685036,"remaining_time":28.52370354},
{"learn":[9.285412357],"iteration":452,"passed_time":23.57666207,"remaining_time":28.46894957},
{"learn":[9.280081107],"iteration":453,"passed_time":23.62568801,"remaining_time":28.41327237},
{"learn":[9.275227425],"iteration":454,"passed_time":23.67411107,"remaining_time":28.35690227},
{"learn":[9.271207859],"iteration":455,"passed_time":23.7224145,"remaining_time":28.30042432},
{"learn":[9.26383281],"iteration":456,"passed_time":23.77123806,"remaining_time":28.24460014},
{"learn":[9.256824853],"iteration":457,"passed_time":23.82074227,"remaining_time":28.18961203},
{"learn":[9.252708999],"iteration":458,"passed_time":23.86974883,"remaining_time":28.13406125},
{"learn":[9.247773251],"iteration":459,"passed_time":23.92015222,"remaining_time":28.08017869},
{"learn":[9.243220795],"iteration":460,"passed_time":23.96989467,"remaining_time":28.02553846},
{"learn":[9.236881452],"iteration":461,"passed_time":24.01852033,"remaining_time":27.96961891},
{"learn":[9.233613841],"iteration":462,"passed_time":24.06630463,"remaining_time":27.91275505},
{"learn":[9.229558409],"iteration":463,"passed_time":24.11473292,"remaining_time":27.85667424},
{"learn":[9.222446238],"iteration":464,"passed_time":24.1632691,"remaining_time":27.80075047},
{"learn":[9.219439697],"iteration":465,"passed_time":24.21145762,"remaining_time":27.74446002},
{"learn":[9.213757882],"iteration":466,"passed_time":24.2595802,"remaining_time":27.68812901},
{"learn":[9.209801254],"iteration":467,"passed_time":24.30961321,"remaining_time":27.63400477},
{"learn":[9.205387896],"iteration":468,"passed_time":24.35868591,"remaining_time":27.5788107},
{"learn":[9.199045187],"iteration":469,"passed_time":24.40731483,"remaining_time":27.52314225},
{"learn":[9.195643957],"iteration":470,"passed_time":24.45666097,"remaining_time":27.46830925},
{"learn":[9.188701659],"iteration":471,"passed_time":24.50544073,"remaining_time":27.4128659},
{"learn":[9.185382152],"iteration":472,"passed_time":24.55385483,"remaining_time":27.35704333},
{"learn":[9.178608466],"iteration":473,"passed_time":24.60144671,"remaining_time":27.3003396},
{"learn":[9.175189016],"iteration":474,"passed_time":24.64972824,"remaining_time":27.24443648},
{"learn":[9.168814729],"iteration":475,"passed_time":24.69775525,"remaining_time":27.18828519},
{"learn":[9.166432723],"iteration":476,"passed_time":24.74638435,"remaining_time":27.13282812},
{"learn":[9.159471602],"iteration":477,"passed_time":24.79492308,"remaining_time":27.07730094},
{"learn":[9.154571222],"iteration":478,"passed_time":24.84293204,"remaining_time":27.0212267},
{"learn":[9.146219035],"iteration":479,"passed_time":24.89171793,"remaining_time":26.96602776},
{"learn":[9.1390366],"iteration":480,"passed_time":24.93906074,"remaining_time":26.90929839},
{"learn":[9.132097414],"iteration":481,"passed_time":24.98756081,"remaining_time":26.85385166},
{"learn":[9.126494401],"iteration":482,"passed_time":25.03604098,"remaining_time":26.79841239},
{"learn":[9.1198732],"iteration":483,"passed_time":25.0845588,"remaining_time":26.74304202},
{"learn":[9.115553225],"iteration":484,"passed_time":25.13284461,"remaining_time":26.68745355},
{"learn":[9.111849113],"iteration":485,"passed_time":25.18165409,"remaining_time":26.63244898},
{"learn":[9.108792235],"iteration":486,"passed_time":25.22976061,"remaining_time":26.57672935},
{"learn":[9.100529573],"iteration":487,"passed_time":25.27872954,"remaining_time":26.52194574},
{"learn":[9.095114162],"iteration":488,"passed_time":25.32756196,"remaining_time":26.46704327},
{"learn":[9.09021897],"iteration":489,"passed_time":25.37690965,"remaining_time":26.41270188},
{"learn":[9.086241868],"iteration":490,"passed_time":25.42523532,"remaining_time":26.35732134},
{"learn":[9.082651324],"iteration":491,"passed_time":25.47372951,"remaining_time":26.30214347},
{"learn":[9.076276475],"iteration":492,"passed_time":25.5229622,"remaining_time":26.2477522},
{"learn":[9.072607214],"iteration":493,"passed_time":25.57190331,"remaining_time":26.19308314},
{"learn":[9.067583106],"iteration":494,"passed_time":25.62048691,"remaining_time":26.13807251},
{"learn":[9.062565578],"iteration":495,"passed_time":25.66858862,"remaining_time":26.08259811},
{"learn":[9.056368058],"iteration":496,"passed_time":25.71687435,"remaining_time":26.02733963},
{"learn":[9.048748775],"iteration":497,"passed_time":25.76659915,"remaining_time":25.97355979},
{"learn":[9.046880984],"iteration":498,"passed_time":25.815861,"remaining_time":25.91933139},
{"learn":[9.044886521],"iteration":499,"passed_time":25.86550582,"remaining_time":25.86550582},
{"learn":[9.042018368],"iteration":500,"passed_time":25.91417738,"remaining_time":25.81072757},
{"learn":[9.038120303],"iteration":501,"passed_time":25.96263397,"remaining_time":25.7557604},
{"learn":[9.030365444],"iteration":502,"passed_time":26.01195583,"remaining_time":25.70167405},
{"learn":[9.028137297],"iteration":503,"passed_time":26.0603355,"remaining_time":25.64667938},
{"learn":[9.022254776],"iteration":504,"passed_time":26.10853577,"remaining_time":25.59153507},
{"learn":[9.017047504],"iteration":505,"passed_time":26.15662536,"remaining_time":25.53631013},
{"learn":[9.01453772],"iteration":506,"passed_time":26.20487995,"remaining_time":25.48127379},
{"learn":[9.011366191],"iteration":507,"passed_time":26.25328984,"remaining_time":25.42641457},
{"learn":[9.00648321],"iteration":508,"passed_time":26.30354137,"remaining_time":25.3733572},
{"learn":[9.000869026],"iteration":509,"passed_time":26.35285456,"remaining_time":25.31940928},
{"learn":[8.998307275],"iteration":510,"passed_time":26.40144256,"remaining_time":25.26478555},
{"learn":[8.993466567],"iteration":511,"passed_time":26.45007315,"remaining_time":25.21022597},
{"learn":[8.990693798],"iteration":512,"passed_time":26.49860191,"remaining_time":25.15559284},
{"learn":[8.986263445],"iteration":513,"passed_time":26.54827794,"remaining_time":25.10206825},
{"learn":[8.979881268],"iteration":514,"passed_time":26.59640887,"remaining_time":25.0471035},
{"learn":[8.977012012],"iteration":515,"passed_time":26.64457646,"remaining_time":24.99219963},
{"learn":[8.973091581],"iteration":516,"passed_time":26.69270662,"remaining_time":24.93728684},
{"learn":[8.968329387],"iteration":517,"passed_time":26.74134418,"remaining_time":24.88287238},
{"learn":[8.960366725],"iteration":518,"passed_time":26.79256234,"remaining_time":24.83087184},
{"learn":[8.956185127],"iteration":519,"passed_time":26.84317875,"remaining_time":24.77831885},
{"learn":[8.954302073],"iteration":520,"passed_time":26.89228074,"remaining_time":24.72438095},
{"learn":[8.948861886],"iteration":521,"passed_time":26.94031326,"remaining_time":24.66948226},
{"learn":[8.944732063],"iteration":522,"passed_time":26.98919842,"remaining_time":24.61538747},
{"learn":[8.938739625],"iteration":523,"passed_time":27.03867463,"remaining_time":24.56184948},
{"learn":[8.933594775],"iteration":524,"passed_time":27.08889346,"remaining_time":24.50899884},
{"learn":[8.927469266],"iteration":525,"passed_time":27.1435312,"remaining_time":24.46014028},
{"learn":[8.922536415],"iteration":526,"passed_time":27.20061486,"remaining_time":24.41345508},
{"learn":[8.918848589],"iteration":527,"passed_time":27.25928831,"remaining_time":24.36815167},
{"learn":[8.916299119],"iteration":528,"passed_time":27.32161584,"remaining_time":24.32605116},
{"learn":[8.911410201],"iteration":529,"passed_time":27.3852794,"remaining_time":24.28505909},
{"learn":[8.905536752],"iteration":530,"passed_time":27.4412639,"remaining_time":24.23719919},
{"learn":[8.900745447],"iteration":531,"passed_time":27.49823047,"remaining_time":24.19017267},
{"learn":[8.898078369],"iteration":532,"passed_time":27.55269681,"remaining_time":24.14091822},
{"learn":[8.89250344],"iteration":533,"passed_time":27.60357778,"remaining_time":24.08851544},
{"learn":[8.886065534],"iteration":534,"passed_time":27.65416504,"remaining_time":24.03586307},
{"learn":[8.883836913],"iteration":535,"passed_time":27.70739557,"remaining_time":23.98550661},
{"learn":[8.881037622],"iteration":536,"passed_time":27.75728253,"remaining_time":23.93225663},
{"learn":[8.876716357],"iteration":537,"passed_time":27.80513206,"remaining_time":23.87726954},
{"learn":[8.871909666],"iteration":538,"passed_time":27.85334128,"remaining_time":23.82261657},
{"learn":[8.864129887],"iteration":539,"passed_time":27.90142875,"remaining_time":23.76788375},
{"learn":[8.859703828],"iteration":540,"passed_time":27.94974795,"remaining_time":23.7133721},
{"learn":[8.856748681],"iteration":541,"passed_time":27.99888147,"remaining_time":23.65957143},
{"learn":[8.85177186],"iteration":542,"passed_time":28.05000166,"remaining_time":23.60745996},
{"learn":[8.845968907],"iteration":543,"passed_time":28.09980628,"remaining_time":23.55424938},
{"learn":[8.841052945],"iteration":544,"passed_time":28.14808008,"remaining_time":23.49977328},
{"learn":[8.839194094],"iteration":545,"passed_time":28.20407419,"remaining_time":23.45173934},
{"learn":[8.834419331],"iteration":546,"passed_time":28.25263627,"remaining_time":23.39752145},
{"learn":[8.829391516],"iteration":547,"passed_time":28.30045001,"remaining_time":23.34270694},
{"learn":[8.823049967],"iteration":548,"passed_time":28.35053255,"remaining_time":23.28978175},
{"learn":[8.8187939],"iteration":549,"passed_time":28.39906626,"remaining_time":23.23559967},
{"learn":[8.812793004],"iteration":550,"passed_time":28.44723277,"remaining_time":23.18113886},
{"learn":[8.806549487],"iteration":551,"passed_time":28.49568462,"remaining_time":23.12693245},
{"learn":[8.803137282],"iteration":552,"passed_time":28.54511146,"remaining_time":23.07353494},
{"learn":[8.795023114],"iteration":553,"passed_time":28.59332959,"remaining_time":23.01917869},
{"learn":[8.792789296],"iteration":554,"passed_time":28.64141924,"remaining_time":22.96474155},
{"learn":[8.788308863],"iteration":555,"passed_time":28.6904907,"remaining_time":22.91111128},
{"learn":[8.784597918],"iteration":556,"passed_time":28.73873775,"remaining_time":22.85684169},
{"learn":[8.779668266],"iteration":557,"passed_time":28.78704674,"remaining_time":22.80264276},
{"learn":[8.777380916],"iteration":558,"passed_time":28.83496782,"remaining_time":22.74815887},
{"learn":[8.774990996],"iteration":559,"passed_time":28.88375753,"remaining_time":22.69438091},
{"learn":[8.769678374],"iteration":560,"passed_time":28.9320169,"remaining_time":22.64020574},
{"learn":[8.765530528],"iteration":561,"passed_time":28.979329,"remaining_time":22.58531335},
{"learn":[8.76116359],"iteration":562,"passed_time":29.02836291,"remaining_time":22.53178436},
{"learn":[8.758031394],"iteration":563,"passed_time":29.08569114,"remaining_time":22.48468323},
{"learn":[8.754917957],"iteration":564,"passed_time":29.13406215,"remaining_time":22.43064962},
{"learn":[8.752656335],"iteration":565,"passed_time":29.18262591,"remaining_time":22.37678382},
{"learn":[8.749426692],"iteration":566,"passed_time":29.2304069,"remaining_time":22.32233895},
{"learn":[8.74544441],"iteration":567,"passed_time":29.27912409,"remaining_time":22.26862959},
{"learn":[8.743914688],"iteration":568,"passed_time":29.32729693,"remaining_time":22.21452545},
{"learn":[8.742384694],"iteration":569,"passed_time":29.37686595,"remaining_time":22.16149536},
{"learn":[8.737918645],"iteration":570,"passed_time":29.42529045,"remaining_time":22.10761752},
{"learn":[8.732045052],"iteration":571,"passed_time":29.47318562,"remaining_time":22.05336267},
{"learn":[8.725839129],"iteration":572,"passed_time":29.52188049,"remaining_time":21.99972595},
{"learn":[8.72223465],"iteration":573,"passed_time":29.5707846,"remaining_time":21.94626174},
{"learn":[8.720916748],"iteration":574,"passed_time":29.61962462,"remaining_time":21.89276602},
{"learn":[8.717584241],"iteration":575,"passed_time":29.66809733,"remaining_time":21.83901609},
{"learn":[8.709843664],"iteration":576,"passed_time":29.71749054,"remaining_time":21.78595927},
{"learn":[8.70382125],"iteration":577,"passed_time":29.76568502,"remaining_time":21.73203993},
{"learn":[8.699406451],"iteration":578,"passed_time":29.81386523,"remaining_time":21.67812998},
{"learn":[8.698092289],"iteration":579,"passed_time":29.86175564,"remaining_time":21.62402995},
{"learn":[8.694175511],"iteration":580,"passed_time":29.91062549,"remaining_time":21.57065762},
{"learn":[8.687249466],"iteration":581,"passed_time":29.95987336,"remaining_time":21.51757227},
{"learn":[8.682670849],"iteration":582,"passed_time":30.00822056,"remaining_time":21.46385587},
{"learn":[8.679439982],"iteration":583,"passed_time":30.05733237,"remaining_time":21.41070251},
{"learn":[8.673915831],"iteration":584,"passed_time":30.10580593,"remaining_time":21.35711019},
{"learn":[8.669336394],"iteration":585,"passed_time":30.15503533,"remaining_time":21.30406933},
{"learn":[8.666832362],"iteration":586,"passed_time":30.2040902,"remaining_time":21.25091866},
{"learn":[8.663059075],"iteration":587,"passed_time":30.25366479,"remaining_time":21.19814608},
{"learn":[8.660376987],"iteration":588,"passed_time":30.30309223,"remaining_time":21.14528168},
{"learn":[8.659073975],"iteration":589,"passed_time":30.35485313,"remaining_time":21.09405048},
{"learn":[8.655405946],"iteration":590,"passed_time":30.40324812,"remaining_time":21.04048812},
{"learn":[8.652848798],"iteration":591,"passed_time":30.45160067,"remaining_time":20.98691397},
{"learn":[8.648257162],"iteration":592,"passed_time":30.50036544,"remaining_time":20.93364036},
{"learn":[8.644540972],"iteration":593,"passed_time":30.54902406,"remaining_time":20.88030938},
{"learn":[8.643028796],"iteration":594,"passed_time":30.59752748,"remaining_time":20.82688845},
{"learn":[8.637762087],"iteration":595,"passed_time":30.64589396,"remaining_time":20.77339121},
{"learn":[8.634333533],"iteration":596,"passed_time":30.69455867,"remaining_time":20.72011247},
{"learn":[8.627241561],"iteration":597,"passed_time":30.74355641,"remaining_time":20.66707304},
{"learn":[8.622174914],"iteration":598,"passed_time":30.79130752,"remaining_time":20.61321255},
{"learn":[8.619298137],"iteration":599,"passed_time":30.840282,"remaining_time":20.560188},
{"learn":[8.61594449],"iteration":600,"passed_time":30.88989238,"remaining_time":20.5075991},
{"learn":[8.612147224],"iteration":601,"passed_time":30.9405903,"remaining_time":20.4557391},
{"learn":[8.607814681],"iteration":602,"passed_time":30.99024183,"remaining_time":20.40319404},
{"learn":[8.605231885],"iteration":603,"passed_time":31.04019407,"remaining_time":20.35085572},
{"learn":[8.59861289],"iteration":604,"passed_time":31.08860214,"remaining_time":20.2975171},
{"learn":[8.596098185],"iteration":605,"passed_time":31.13688871,"remaining_time":20.24411576},
{"learn":[8.592475544],"iteration":606,"passed_time":31.18537465,"remaining_time":20.19086036},
{"learn":[8.587918032],"iteration":607,"passed_time":31.23410495,"remaining_time":20.13777819},
{"learn":[8.584647758],"iteration":608,"passed_time":31.28303602,"remaining_time":20.08483922},
{"learn":[8.580501858],"iteration":609,"passed_time":31.33150856,"remaining_time":20.03162023},
{"learn":[8.578666968],"iteration":610,"passed_time":31.40003875,"remaining_time":19.9911867},
{"learn":[8.575340331],"iteration":611,"passed_time":31.45560596,"remaining_time":19.942443},
{"learn":[8.570196865],"iteration":612,"passed_time":31.50568146,"remaining_time":19.89020999},
{"learn":[8.56563467],"iteration":613,"passed_time":31.554546,"remaining_time":19.83722273},
{"learn":[8.562520897],"iteration":614,"passed_time":31.60360329,"remaining_time":19.78436954},
{"learn":[8.557584049],"iteration":615,"passed_time":31.65227899,"remaining_time":19.7312908},
{"learn":[8.554642714],"iteration":616,"passed_time":31.70160698,"remaining_time":19.67863124},
{"learn":[8.550380442],"iteration":617,"passed_time":31.75022709,"remaining_time":19.6255449},
{"learn":[8.545195435],"iteration":618,"passed_time":31.79874656,"remaining_time":19.57241105},
{"learn":[8.539866153],"iteration":619,"passed_time":31.84725839,"remaining_time":19.5192874},
{"learn":[8.537287951],"iteration":620,"passed_time":31.89703158,"remaining_time":19.46694842},
{"learn":[8.532513497],"iteration":621,"passed_time":31.94786123,"remaining_time":19.41525972},
{"learn":[8.52732784],"iteration":622,"passed_time":31.99588307,"remaining_time":19.36187467},
{"learn":[8.524523756],"iteration":623,"passed_time":32.04423038,"remaining_time":19.30870292},
{"learn":[8.522931705],"iteration":624,"passed_time":32.09263647,"remaining_time":19.25558188},
{"learn":[8.515909088],"iteration":625,"passed_time":32.14165768,"remaining_time":19.20284341},
{"learn":[8.512058613],"iteration":626,"passed_time":32.19013906,"remaining_time":19.14979565},
{"learn":[8.509277445],"iteration":627,"passed_time":32.23833182,"remaining_time":19.09659146},
{"learn":[8.505734678],"iteration":628,"passed_time":32.28688577,"remaining_time":19.04361625},
{"learn":[8.500898415],"iteration":629,"passed_time":32.33554815,"remaining_time":18.99071875},
{"learn":[8.497821795],"iteration":630,"passed_time":32.38429949,"remaining_time":18.93788671},
{"learn":[8.490340894],"iteration":631,"passed_time":32.43381503,"remaining_time":18.88551255},
{"learn":[8.488147244],"iteration":632,"passed_time":32.48144183,"remaining_time":18.83205237},
{"learn":[8.486291523],"iteration":633,"passed_time":32.53149471,"remaining_time":18.78001114},
{"learn":[8.480224176],"iteration":634,"passed_time":32.58177167,"remaining_time":18.72810498},
{"learn":[8.478653523],"iteration":635,"passed_time":32.63148,"remaining_time":18.67587849},
{"learn":[8.476666233],"iteration":636,"passed_time":32.67963904,"remaining_time":18.62277704},
{"learn":[8.473652755],"iteration":637,"passed_time":32.72818917,"remaining_time":18.56991298},
{"learn":[8.471015426],"iteration":638,"passed_time":32.77705139,"remaining_time":18.51723873},
{"learn":[8.467969015],"iteration":639,"passed_time":32.83027012,"remaining_time":18.46702694},
{"learn":[8.466288165],"iteration":640,"passed_time":32.88134969,"remaining_time":18.41560771},
{"learn":[8.462778987],"iteration":641,"passed_time":32.93557891,"remaining_time":18.36594587},
{"learn":[8.459334837],"iteration":642,"passed_time":32.9881204,"remaining_time":18.31533279},
{"learn":[8.455040012],"iteration":643,"passed_time":33.04128222,"remaining_time":18.26505663},
{"learn":[8.449883556],"iteration":644,"passed_time":33.09438807,"remaining_time":18.21474072},
{"learn":[8.443312491],"iteration":645,"passed_time":33.14949637,"remaining_time":18.16551349},
{"learn":[8.438904376],"iteration":646,"passed_time":33.2051075,"remaining_time":18.11654242},
{"learn":[8.435555202],"iteration":647,"passed_time":33.26179833,"remaining_time":18.06813736},
{"learn":[8.430863785],"iteration":648,"passed_time":33.32629743,"remaining_time":18.02392974},
{"learn":[8.426004349],"iteration":649,"passed_time":33.39706597,"remaining_time":17.98303552},
{"learn":[8.420752963],"iteration":650,"passed_time":33.45834315,"remaining_time":17.93696123},
{"learn":[8.415335085],"iteration":651,"passed_time":33.51916423,"remaining_time":17.89059686},
{"learn":[8.413047915],"iteration":652,"passed_time":33.5802747,"remaining_time":17.84434199},
{"learn":[8.408234182],"iteration":653,"passed_time":33.63192981,"remaining_time":17.79303932},
{"learn":[8.404835617],"iteration":654,"passed_time":33.68006015,"remaining_time":17.73987901},
{"learn":[8.399864095],"iteration":655,"passed_time":33.72858512,"remaining_time":17.68694098},
{"learn":[8.393859847],"iteration":656,"passed_time":33.77800519,"remaining_time":17.63448369},
{"learn":[8.391964484],"iteration":657,"passed_time":33.82669293,"remaining_time":17.58165499},
{"learn":[8.389039051],"iteration":658,"passed_time":33.87564825,"remaining_time":17.52897732},
{"learn":[8.385009549],"iteration":659,"passed_time":33.92422545,"remaining_time":17.47611614},
{"learn":[8.379820127],"iteration":660,"passed_time":33.97130642,"remaining_time":17.42250057},
{"learn":[8.3783926],"iteration":661,"passed_time":34.02025566,"remaining_time":17.36985863},
{"learn":[8.373780003],"iteration":662,"passed_time":34.06931756,"remaining_time":17.31728509},
{"learn":[8.367679044],"iteration":663,"passed_time":34.11843411,"remaining_time":17.26474979},
{"learn":[8.363479295],"iteration":664,"passed_time":34.16731218,"remaining_time":17.21210463},
{"learn":[8.359559874],"iteration":665,"passed_time":34.21767034,"remaining_time":17.16021305},
{"learn":[8.354421742],"iteration":666,"passed_time":34.26881548,"remaining_time":17.10871898},
{"learn":[8.34946495],"iteration":667,"passed_time":34.3264137,"remaining_time":17.06043316},
{"learn":[8.343799515],"iteration":668,"passed_time":34.38788116,"remaining_time":17.01403388},
{"learn":[8.341618337],"iteration":669,"passed_time":34.4430639,"remaining_time":16.96449416},
{"learn":[8.338288338],"iteration":670,"passed_time":34.50017871,"remaining_time":16.91588494},
{"learn":[8.335916108],"iteration":671,"passed_time":34.5579776,"remaining_time":16.8675843},
{"learn":[8.333536015],"iteration":672,"passed_time":34.60796661,"remaining_time":16.81546075},
{"learn":[8.330639331],"iteration":673,"passed_time":34.65826443,"remaining_time":16.76349288},
{"learn":[8.325959105],"iteration":674,"passed_time":34.7059503,"remaining_time":16.71027237},
{"learn":[8.321871441],"iteration":675,"passed_time":34.7544226,"remaining_time":16.65744515},
{"learn":[8.317243512],"iteration":676,"passed_time":34.80164206,"remaining_time":16.60403306},
{"learn":[8.314978301],"iteration":677,"passed_time":34.85093126,"remaining_time":16.55162222},
{"learn":[8.313271253],"iteration":678,"passed_time":34.89975489,"remaining_time":16.49900047},
{"learn":[8.309381824],"iteration":679,"passed_time":34.94841012,"remaining_time":16.44631065},
{"learn":[8.306537865],"iteration":680,"passed_time":34.99644171,"remaining_time":16.39334054},
{"learn":[8.30223146],"iteration":681,"passed_time":35.04615379,"remaining_time":16.34116848},
{"learn":[8.298691263],"iteration":682,"passed_time":35.09665311,"remaining_time":16.28936901},
{"learn":[8.294946153],"iteration":683,"passed_time":35.14780676,"remaining_time":16.23787564},
{"learn":[8.291083337],"iteration":684,"passed_time":35.19847819,"remaining_time":16.1861615},
{"learn":[8.287776431],"iteration":685,"passed_time":35.24898036,"remaining_time":16.13437293},
{"learn":[8.282971859],"iteration":686,"passed_time":35.30463647,"remaining_time":16.08493627},
{"learn":[8.279213516],"iteration":687,"passed_time":35.36345836,"remaining_time":16.03691716},
{"learn":[8.275109433],"iteration":688,"passed_time":35.41999642,"remaining_time":15.98783583},
{"learn":[8.27227942],"iteration":689,"passed_time":35.47355677,"remaining_time":15.93739507},
{"learn":[8.268725602],"iteration":690,"passed_time":35.52818235,"remaining_time":15.88742163},
{"learn":[8.264829579],"iteration":691,"passed_time":35.5767733,"remaining_time":15.83474881},
{"learn":[8.260741789],"iteration":692,"passed_time":35.62529332,"remaining_time":15.78205635},
{"learn":[8.25769464],"iteration":693,"passed_time":35.67275096,"remaining_time":15.72890748},
{"learn":[8.254384301],"iteration":694,"passed_time":35.721739,"remaining_time":15.67644661},
{"learn":[8.250662081],"iteration":695,"passed_time":35.76975219,"remaining_time":15.62356992},
{"learn":[8.247249692],"iteration":696,"passed_time":35.8182756,"remaining_time":15.57092899},
{"learn":[8.244978354],"iteration":697,"passed_time":35.86746282,"remaining_time":15.51858707},
{"learn":[8.239621204],"iteration":698,"passed_time":35.91646267,"remaining_time":15.46617348},
{"learn":[8.23490953],"iteration":699,"passed_time":35.96836571,"remaining_time":15.41501387},
{"learn":[8.232148537],"iteration":700,"passed_time":36.02706248,"remaining_time":15.3667499},
{"learn":[8.2275611],"iteration":701,"passed_time":36.07556716,"remaining_time":15.31412965},
{"learn":[8.221199417],"iteration":702,"passed_time":36.12382952,"remaining_time":15.26141873},
{"learn":[8.218989841],"iteration":703,"passed_time":36.17225033,"remaining_time":15.20878707},
{"learn":[8.213908648],"iteration":704,"passed_time":36.22138039,"remaining_time":15.15646414},
{"learn":[8.210793807],"iteration":705,"passed_time":36.26988816,"remaining_time":15.1038911},
{"learn":[8.208049946],"iteration":706,"passed_time":36.31798272,"remaining_time":15.05115833},
{"learn":[8.2065866],"iteration":707,"passed_time":36.36646967,"remaining_time":14.99860049},
{"learn":[8.201607206],"iteration":708,"passed_time":36.4159936,"remaining_time":14.94647974},
{"learn":[8.198608625],"iteration":709,"passed_time":36.46429953,"remaining_time":14.89386882},
{"learn":[8.193434448],"iteration":710,"passed_time":36.51360347,"remaining_time":14.84167567},
{"learn":[8.190621162],"iteration":711,"passed_time":36.56179207,"remaining_time":14.78903949},
{"learn":[8.187518417],"iteration":712,"passed_time":36.60992451,"remaining_time":14.73639318},
{"learn":[8.185578339],"iteration":713,"passed_time":36.65795609,"remaining_time":14.68371911},
{"learn":[8.180958519],"iteration":714,"passed_time":36.70663314,"remaining_time":14.63131531},
{"learn":[8.177991266],"iteration":715,"passed_time":36.75506577,"remaining_time":14.57882497},
{"learn":[8.17230817],"iteration":716,"passed_time":36.80360589,"remaining_time":14.52638838},
{"learn":[8.166880117],"iteration":717,"passed_time":36.85223514,"remaining_time":14.47399765},
{"learn":[8.162361781],"iteration":718,"passed_time":36.90124959,"remaining_time":14.42176792},
{"learn":[8.160002129],"iteration":719,"passed_time":36.9497696,"remaining_time":14.36935485},
{"learn":[8.157571427],"iteration":720,"passed_time":36.99908693,"remaining_time":14.3172611},
{"learn":[8.15297483],"iteration":721,"passed_time":37.04894645,"remaining_time":14.26538381},
{"learn":[8.149484026],"iteration":722,"passed_time":37.09985276,"remaining_time":14.21391316},
{"learn":[8.148146666],"iteration":723,"passed_time":37.152535,"remaining_time":14.16312108},
{"learn":[8.145178668],"iteration":724,"passed_time":37.20378004,"remaining_time":14.11177864},
{"learn":[8.140132041],"iteration":725,"passed_time":37.25400374,"remaining_time":14.060051},
{"learn":[8.136876243],"iteration":726,"passed_time":37.30532486,"remaining_time":14.0087396},
{"learn":[8.1324872],"iteration":727,"passed_time":37.35833408,"remaining_time":13.95805889},
{"learn":[8.126268086],"iteration":728,"passed_time":37.40868081,"remaining_time":13.90638203},
{"learn":[8.124100442],"iteration":729,"passed_time":37.45735758,"remaining_time":13.85409116},
{"learn":[8.1193673],"iteration":730,"passed_time":37.50708238,"remaining_time":13.80219584},
{"learn":[8.115902279],"iteration":731,"passed_time":37.55825047,"remaining_time":13.75083487},
{"learn":[8.112060912],"iteration":732,"passed_time":37.61019348,"remaining_time":13.6997567},
{"learn":[8.110206182],"iteration":733,"passed_time":37.65842015,"remaining_time":13.64732937},
{"learn":[8.106645258],"iteration":734,"passed_time":37.70923533,"remaining_time":13.59584675},
{"learn":[8.104726923],"iteration":735,"passed_time":37.75862056,"remaining_time":13.54385303},
{"learn":[8.098307225],"iteration":736,"passed_time":37.81022598,"remaining_time":13.49265866},
{"learn":[8.095993955],"iteration":737,"passed_time":37.86109325,"remaining_time":13.44120113},
{"learn":[8.090373672],"iteration":738,"passed_time":37.91355853,"remaining_time":13.39030958},
{"learn":[8.088307759],"iteration":739,"passed_time":37.96378137,"remaining_time":13.33862589},
{"learn":[8.083684117],"iteration":740,"passed_time":38.01195515,"remaining_time":13.28622994},
{"learn":[8.081713813],"iteration":741,"passed_time":38.06359422,"remaining_time":13.23505028},
{"learn":[8.078179514],"iteration":742,"passed_time":38.11387941,"remaining_time":13.18340109},
{"learn":[8.073683373],"iteration":743,"passed_time":38.163951,"remaining_time":13.13168206},
{"learn":[8.069714762],"iteration":744,"passed_time":38.2120478,"remaining_time":13.07929153},
{"learn":[8.065166753],"iteration":745,"passed_time":38.26165101,"remaining_time":13.02742541},
{"learn":[8.061975296],"iteration":746,"passed_time":38.31009073,"remaining_time":12.97517129},
{"learn":[8.056335488],"iteration":747,"passed_time":38.35895023,"remaining_time":12.92306879},
{"learn":[8.054102783],"iteration":748,"passed_time":38.40814885,"remaining_time":12.8710886},
{"learn":[8.046956265],"iteration":749,"passed_time":38.45712676,"remaining_time":12.81904225},
{"learn":[8.045286348],"iteration":750,"passed_time":38.5053168,"remaining_time":12.76674285},
{"learn":[8.043102194],"iteration":751,"passed_time":38.55430231,"remaining_time":12.71471672},
{"learn":[8.041245001],"iteration":752,"passed_time":38.60329108,"remaining_time":12.66269973},
{"learn":[8.039987201],"iteration":753,"passed_time":38.65139498,"remaining_time":12.61040208},
{"learn":[8.037713316],"iteration":754,"passed_time":38.71300417,"remaining_time":12.56249804},
{"learn":[8.033405755],"iteration":755,"passed_time":38.79540329,"remaining_time":12.52126773},
{"learn":[8.029842014],"iteration":756,"passed_time":38.84369323,"remaining_time":12.46897947},
{"learn":[8.022790245],"iteration":757,"passed_time":38.89326586,"remaining_time":12.41711126},
{"learn":[8.019088407],"iteration":758,"passed_time":38.94193478,"remaining_time":12.36496216},
{"learn":[8.015647263],"iteration":759,"passed_time":38.99120229,"remaining_time":12.31301125},
{"learn":[8.011026426],"iteration":760,"passed_time":39.04080774,"remaining_time":12.26117352},
{"learn":[8.008136314],"iteration":761,"passed_time":39.09327589,"remaining_time":12.21023578},
{"learn":[8.003797964],"iteration":762,"passed_time":39.14147351,"remaining_time":12.15796752},
{"learn":[8.001366254],"iteration":763,"passed_time":39.19083075,"remaining_time":12.10606814},
{"learn":[7.998095307],"iteration":764,"passed_time":39.24082769,"remaining_time":12.0543719},
{"learn":[7.995310721],"iteration":765,"passed_time":39.29481824,"remaining_time":12.00390009},
{"learn":[7.99197118],"iteration":766,"passed_time":39.34366579,"remaining_time":11.95185675},
{"learn":[7.987329982],"iteration":767,"passed_time":39.39349755,"remaining_time":11.90011905},
{"learn":[7.98466419],"iteration":768,"passed_time":39.44358641,"remaining_time":11.84846354},
{"learn":[7.982284057],"iteration":769,"passed_time":39.49249792,"remaining_time":11.79646042},
{"learn":[7.98164995],"iteration":770,"passed_time":39.54062598,"remaining_time":11.74423262},
{"learn":[7.979522521],"iteration":771,"passed_time":39.58948406,"remaining_time":11.69223104},
{"learn":[7.977439384],"iteration":772,"passed_time":39.6378998,"remaining_time":11.6401077},
{"learn":[7.975426894],"iteration":773,"passed_time":39.68620301,"remaining_time":11.58796109},
{"learn":[7.973831242],"iteration":774,"passed_time":39.73554197,"remaining_time":11.53612509},
{"learn":[7.969453746],"iteration":775,"passed_time":39.78529681,"remaining_time":11.48441557},
{"learn":[7.963872213],"iteration":776,"passed_time":39.83365649,"remaining_time":11.43231068},
{"learn":[7.96171815],"iteration":777,"passed_time":39.88218576,"remaining_time":11.3802638},
{"learn":[7.958635374],"iteration":778,"passed_time":39.93141359,"remaining_time":11.32842414},
{"learn":[7.953771754],"iteration":779,"passed_time":39.98002409,"remaining_time":11.27641705},
{"learn":[7.951103151],"iteration":780,"passed_time":40.02827256,"remaining_time":11.22431715},
{"learn":[7.949094438],"iteration":781,"passed_time":40.07685338,"remaining_time":11.17231974},
{"learn":[7.945101139],"iteration":782,"passed_time":40.1264959,"remaining_time":11.1206253},
{"learn":[7.943047667],"iteration":783,"passed_time":40.17448152,"remaining_time":11.0684796},
{"learn":[7.939418674],"iteration":784,"passed_time":40.22324697,"remaining_time":11.01655809},
{"learn":[7.93541679],"iteration":785,"passed_time":40.27157974,"remaining_time":10.9645268},
{"learn":[7.932529494],"iteration":786,"passed_time":40.320473,"remaining_time":10.91265661},
{"learn":[7.930335359],"iteration":787,"passed_time":40.36991023,"remaining_time":10.86094032},
{"learn":[7.927656266],"iteration":788,"passed_time":40.41896516,"remaining_time":10.80912757},
{"learn":[7.924347729],"iteration":789,"passed_time":40.46768413,"remaining_time":10.75723249},
{"learn":[7.92048917],"iteration":790,"passed_time":40.51628809,"remaining_time":10.70531506},
{"learn":[7.919008908],"iteration":791,"passed_time":40.56428514,"remaining_time":10.6532466},
{"learn":[7.91799869],"iteration":792,"passed_time":40.61317552,"remaining_time":10.6014216},
{"learn":[7.91561689],"iteration":793,"passed_time":40.66178692,"remaining_time":10.54953162},
{"learn":[7.909914121],"iteration":794,"passed_time":40.71009918,"remaining_time":10.49757274},
{"learn":[7.905096438],"iteration":795,"passed_time":40.75983729,"remaining_time":10.44598845},
{"learn":[7.899103933],"iteration":796,"passed_time":40.80757731,"remaining_time":10.39389987},
{"learn":[7.897289007],"iteration":797,"passed_time":40.85620238,"remaining_time":10.34204622},
{"learn":[7.89265558],"iteration":798,"passed_time":40.90452415,"remaining_time":10.29012435},
{"learn":[7.890745036],"iteration":799,"passed_time":40.95281608,"remaining_time":10.23820402},
{"learn":[7.888197542],"iteration":800,"passed_time":41.00132857,"remaining_time":10.18634755},
{"learn":[7.884748401],"iteration":801,"passed_time":41.04999176,"remaining_time":10.13453662},
{"learn":[7.88294542],"iteration":802,"passed_time":41.09863859,"remaining_time":10.08272952},
{"learn":[7.88039949],"iteration":803,"passed_time":41.14800315,"remaining_time":10.03110524},
{"learn":[7.87847265],"iteration":804,"passed_time":41.19686181,"remaining_time":9.979364041},
{"learn":[7.87436005],"iteration":805,"passed_time":41.24640367,"remaining_time":9.927794431},
{"learn":[7.870530842],"iteration":806,"passed_time":41.29538973,"remaining_time":9.876096925},
{"learn":[7.865418635],"iteration":807,"passed_time":41.34420794,"remaining_time":9.824366242},
{"learn":[7.86397501],"iteration":808,"passed_time":41.3922872,"remaining_time":9.772468301},
{"learn":[7.862802088],"iteration":809,"passed_time":41.44182506,"remaining_time":9.720921928},
{"learn":[7.861645878],"iteration":810,"passed_time":41.49051351,"remaining_time":9.669182556},
{"learn":[7.858479163],"iteration":811,"passed_time":41.53876756,"remaining_time":9.617350124},
{"learn":[7.854392678],"iteration":812,"passed_time":41.58750341,"remaining_time":9.565637316},
{"learn":[7.850317227],"iteration":813,"passed_time":41.63644497,"remaining_time":9.513978826},
{"learn":[7.845402718],"iteration":814,"passed_time":41.68624983,"remaining_time":9.462522967},
{"learn":[7.840663704],"iteration":815,"passed_time":41.73624334,"remaining_time":9.411113695},
{"learn":[7.838396122],"iteration":816,"passed_time":41.78540695,"remaining_time":9.359521997},
{"learn":[7.834540506],"iteration":817,"passed_time":41.83682252,"remaining_time":9.308437284},
{"learn":[7.832919506],"iteration":818,"passed_time":41.88593986,"remaining_time":9.256843852},
{"learn":[7.829136663],"iteration":819,"passed_time":41.93421998,"remaining_time":9.205072678},
{"learn":[7.823966399],"iteration":820,"passed_time":41.98304481,"remaining_time":9.15342877},
{"learn":[7.822687667],"iteration":821,"passed_time":42.03137646,"remaining_time":9.101684926},
{"learn":[7.81825741],"iteration":822,"passed_time":42.07985435,"remaining_time":9.049980826},
{"learn":[7.815688222],"iteration":823,"passed_time":42.12842546,"remaining_time":8.998304468},
{"learn":[7.812598718],"iteration":824,"passed_time":42.1774605,"remaining_time":8.946734045},
{"learn":[7.80827267],"iteration":825,"passed_time":42.22630564,"remaining_time":8.89512976},
{"learn":[7.802719999],"iteration":826,"passed_time":42.27544177,"remaining_time":8.843593018},
{"learn":[7.798876527],"iteration":827,"passed_time":42.32429438,"remaining_time":8.79200318},
{"learn":[7.795153552],"iteration":828,"passed_time":42.37359928,"remaining_time":8.740513242},
{"learn":[7.792333154],"iteration":829,"passed_time":42.422193,"remaining_time":8.688882904},
{"learn":[7.790375827],"iteration":830,"passed_time":42.47178811,"remaining_time":8.637463526},
{"learn":[7.787993727],"iteration":831,"passed_time":42.52142198,"remaining_time":8.586056362},
{"learn":[7.784778493],"iteration":832,"passed_time":42.5700456,"remaining_time":8.534450918},
{"learn":[7.783230838],"iteration":833,"passed_time":42.61928143,"remaining_time":8.482974482},
{"learn":[7.779079193],"iteration":834,"passed_time":42.66992596,"remaining_time":8.431781777},
{"learn":[7.778025811],"iteration":835,"passed_time":42.71832437,"remaining_time":8.380149758},
{"learn":[7.775645402],"iteration":836,"passed_time":42.76845111,"remaining_time":8.328862045},
{"learn":[7.773869003],"iteration":837,"passed_time":42.8173538,"remaining_time":8.277340473},
{"learn":[7.77172807],"iteration":838,"passed_time":42.86648692,"remaining_time":8.225869361},
{"learn":[7.770600059],"iteration":839,"passed_time":42.91480525,"remaining_time":8.17424862},
{"learn":[7.768096586],"iteration":840,"passed_time":42.9654975,"remaining_time":8.123084545},
{"learn":[7.766118716],"iteration":841,"passed_time":43.0138326,"remaining_time":8.071479277},
{"learn":[7.764235373],"iteration":842,"passed_time":43.06244643,"remaining_time":8.019933677},
{"learn":[7.761809745],"iteration":843,"passed_time":43.11033099,"remaining_time":7.968260231},
{"learn":[7.758005698],"iteration":844,"passed_time":43.16076538,"remaining_time":7.917063472},
{"learn":[7.755184235],"iteration":845,"passed_time":43.2090739,"remaining_time":7.865481538},
{"learn":[7.751901831],"iteration":846,"passed_time":43.25724396,"remaining_time":7.813882321},
{"learn":[7.749785543],"iteration":847,"passed_time":43.30621034,"remaining_time":7.762433929},
{"learn":[7.746146583],"iteration":848,"passed_time":43.35768203,"remaining_time":7.711436969},
{"learn":[7.743857862],"iteration":849,"passed_time":43.40801015,"remaining_time":7.660237086},
{"learn":[7.738082827],"iteration":850,"passed_time":43.45769676,"remaining_time":7.60892693},
{"learn":[7.734368419],"iteration":851,"passed_time":43.50872998,"remaining_time":7.557854503},
{"learn":[7.73106198],"iteration":852,"passed_time":43.55717701,"remaining_time":7.506336483},
{"learn":[7.726210379],"iteration":853,"passed_time":43.6067353,"remaining_time":7.455015636},
{"learn":[7.723927284],"iteration":854,"passed_time":43.65560201,"remaining_time":7.403581627},
{"learn":[7.721356175],"iteration":855,"passed_time":43.70355815,"remaining_time":7.352000436},
{"learn":[7.719526596],"iteration":856,"passed_time":43.75149666,"remaining_time":7.300424763},
{"learn":[7.717880865],"iteration":857,"passed_time":43.79995525,"remaining_time":7.248943643},
{"learn":[7.715034702],"iteration":858,"passed_time":43.84820699,"remaining_time":7.197435606},
{"learn":[7.711006566],"iteration":859,"passed_time":43.8967074,"remaining_time":7.145975623},
{"learn":[7.707615938],"iteration":860,"passed_time":43.94679252,"remaining_time":7.094778351},
{"learn":[7.705525007],"iteration":861,"passed_time":43.9970702,"remaining_time":7.043614487},
{"learn":[7.702506445],"iteration":862,"passed_time":44.04722516,"remaining_time":6.992433194},
{"learn":[7.697076028],"iteration":863,"passed_time":44.0975209,"remaining_time":6.941276438},
{"learn":[7.69336281],"iteration":864,"passed_time":44.14705325,"remaining_time":6.89000253},
{"learn":[7.691511617],"iteration":865,"passed_time":44.19518322,"remaining_time":6.838515648},
{"learn":[7.689419904],"iteration":866,"passed_time":44.24412489,"remaining_time":6.787161027},
{"learn":[7.683298048],"iteration":867,"passed_time":44.29261884,"remaining_time":6.735743879},
{"learn":[7.680865663],"iteration":868,"passed_time":44.34095476,"remaining_time":6.684309637},
{"learn":[7.677308343],"iteration":869,"passed_time":44.38907358,"remaining_time":6.632850076},
{"learn":[7.67404453],"iteration":870,"passed_time":44.43752651,"remaining_time":6.581447668},
{"learn":[7.670799557],"iteration":871,"passed_time":44.48805582,"remaining_time":6.530356818},
{"learn":[7.666492766],"iteration":872,"passed_time":44.53652777,"remaining_time":6.478967957},
{"learn":[7.662115505],"iteration":873,"passed_time":44.58497288,"remaining_time":6.427581902},
{"learn":[7.660268],"iteration":874,"passed_time":44.63312547,"remaining_time":6.376160782},
{"learn":[7.65705657],"iteration":875,"passed_time":44.68324286,"remaining_time":6.325025246},
{"learn":[7.655336758],"iteration":876,"passed_time":44.73184523,"remaining_time":6.273679548},
{"learn":[7.651533863],"iteration":877,"passed_time":44.78068205,"remaining_time":6.222372677},
{"learn":[7.64695962],"iteration":878,"passed_time":44.82911034,"remaining_time":6.17101519},
{"learn":[7.646407388],"iteration":879,"passed_time":44.87731397,"remaining_time":6.119633723},
{"learn":[7.643490582],"iteration":880,"passed_time":44.9260706,"remaining_time":6.068334168},
{"learn":[7.641076612],"iteration":881,"passed_time":44.97502307,"remaining_time":6.017066579},
{"learn":[7.638492589],"iteration":882,"passed_time":45.02384107,"remaining_time":5.965786416},
{"learn":[7.636420433],"iteration":883,"passed_time":45.07249093,"remaining_time":5.91448976},
{"learn":[7.632690431],"iteration":884,"passed_time":45.12222941,"remaining_time":5.863340545},
{"learn":[7.6316083],"iteration":885,"passed_time":45.17069229,"remaining_time":5.812030384},
{"learn":[7.626169214],"iteration":886,"passed_time":45.21937791,"remaining_time":5.760755021},
{"learn":[7.620174346],"iteration":887,"passed_time":45.26766138,"remaining_time":5.709434769},
{"learn":[7.616598053],"iteration":888,"passed_time":45.31694501,"remaining_time":5.658246227},
{"learn":[7.61138878],"iteration":889,"passed_time":45.36635968,"remaining_time":5.607078163},
{"learn":[7.609065135],"iteration":890,"passed_time":45.41725855,"remaining_time":5.556095603},
{"learn":[7.603511326],"iteration":891,"passed_time":45.46606245,"remaining_time":5.504859579},
{"learn":[7.601382414],"iteration":892,"passed_time":45.51409866,"remaining_time":5.453537018},
{"learn":[7.599472273],"iteration":893,"passed_time":45.56224859,"remaining_time":5.402235292},
{"learn":[7.594685678],"iteration":894,"passed_time":45.61222995,"remaining_time":5.351155469},
{"learn":[7.591394922],"iteration":895,"passed_time":45.66104109,"remaining_time":5.299942269},
{"learn":[7.58826085],"iteration":896,"passed_time":45.709368,"remaining_time":5.248678822},
{"learn":[7.586709912],"iteration":897,"passed_time":45.75753233,"remaining_time":5.197403449},
{"learn":[7.584205674],"iteration":898,"passed_time":45.8057643,"remaining_time":5.146142596},
{"learn":[7.582416434],"iteration":899,"passed_time":45.85359421,"remaining_time":5.094843801},
{"learn":[7.579670586],"iteration":900,"passed_time":45.90198403,"remaining_time":5.043614227},
{"learn":[7.578332119],"iteration":901,"passed_time":45.95054223,"remaining_time":4.992409245},
{"learn":[7.572486043],"iteration":902,"passed_time":45.99904229,"remaining_time":4.941203878},
{"learn":[7.568061905],"iteration":903,"passed_time":46.04776079,"remaining_time":4.890027695},
{"learn":[7.564021839],"iteration":904,"passed_time":46.09592824,"remaining_time":4.838799097},
{"learn":[7.560231359],"iteration":905,"passed_time":46.14497513,"remaining_time":4.787668501},
{"learn":[7.55534479],"iteration":906,"passed_time":46.19298351,"remaining_time":4.736436016},
{"learn":[7.553536953],"iteration":907,"passed_time":46.24354197,"remaining_time":4.685469011},
{"learn":[7.548747717],"iteration":908,"passed_time":46.29265747,"remaining_time":4.634358449},
{"learn":[7.543271286],"iteration":909,"passed_time":46.34226673,"remaining_time":4.583301105},
{"learn":[7.538202339],"iteration":910,"passed_time":46.39134195,"remaining_time":4.532194768},
{"learn":[7.535248134],"iteration":911,"passed_time":46.44015196,"remaining_time":4.481067294},
{"learn":[7.532529641],"iteration":912,"passed_time":46.48903962,"remaining_time":4.429952297},
{"learn":[7.532000733],"iteration":913,"passed_time":46.53747566,"remaining_time":4.37879968},
{"learn":[7.530014619],"iteration":914,"passed_time":46.58625887,"remaining_time":4.32768525},
{"learn":[7.526878995],"iteration":915,"passed_time":46.63416529,"remaining_time":4.276495507},
{"learn":[7.525110512],"iteration":916,"passed_time":46.6838493,"remaining_time":4.225473819},
{"learn":[7.524117778],"iteration":917,"passed_time":46.73200012,"remaining_time":4.174318093},
{"learn":[7.521142098],"iteration":918,"passed_time":46.78189238,"remaining_time":4.123322397},
{"learn":[7.518412598],"iteration":919,"passed_time":46.83107097,"remaining_time":4.072267041},
{"learn":[7.514453904],"iteration":920,"passed_time":46.88075635,"remaining_time":4.021259231},
{"learn":[7.512516214],"iteration":921,"passed_time":46.93049487,"remaining_time":3.970258785},
{"learn":[7.509130393],"iteration":922,"passed_time":46.97884586,"remaining_time":3.919145321},
{"learn":[7.506238539],"iteration":923,"passed_time":47.02782821,"remaining_time":3.868089766},
{"learn":[7.501368983],"iteration":924,"passed_time":47.07621614,"remaining_time":3.816990497},
{"learn":[7.498620927],"iteration":925,"passed_time":47.12659258,"remaining_time":3.766055994},
{"learn":[7.494225904],"iteration":926,"passed_time":47.17547366,"remaining_time":3.715004938},
{"learn":[7.489852314],"iteration":927,"passed_time":47.22401704,"remaining_time":3.663932356},
{"learn":[7.485736553],"iteration":928,"passed_time":47.27289398,"remaining_time":3.612890713},
{"learn":[7.483171232],"iteration":929,"passed_time":47.32103554,"remaining_time":3.561798374},
{"learn":[7.478850679],"iteration":930,"passed_time":47.36946744,"remaining_time":3.510733892},
{"learn":[7.4773196],"iteration":931,"passed_time":47.41851994,"remaining_time":3.459720339},
{"learn":[7.474687746],"iteration":932,"passed_time":47.46741623,"remaining_time":3.408699772},
{"learn":[7.47222168],"iteration":933,"passed_time":47.51725058,"remaining_time":3.357750041},
{"learn":[7.468814446],"iteration":934,"passed_time":47.56714923,"remaining_time":3.306807166},
{"learn":[7.467407198],"iteration":935,"passed_time":47.61915263,"remaining_time":3.256010436},
{"learn":[7.464565212],"iteration":936,"passed_time":47.66802313,"remaining_time":3.205000488},
{"learn":[7.46223317],"iteration":937,"passed_time":47.71636084,"remaining_time":3.153959885},
{"learn":[7.460982418],"iteration":938,"passed_time":47.76547488,"remaining_time":3.102975472},
{"learn":[7.459398253],"iteration":939,"passed_time":47.8141864,"remaining_time":3.051969345},
{"learn":[7.454119099],"iteration":940,"passed_time":47.86354915,"remaining_time":3.001008926},
{"learn":[7.451173047],"iteration":941,"passed_time":47.91230132,"remaining_time":2.950014306},
{"learn":[7.447969002],"iteration":942,"passed_time":47.96066291,"remaining_time":2.899000834},
{"learn":[7.446257662],"iteration":943,"passed_time":48.0087458,"remaining_time":2.847976446},
{"learn":[7.444540543],"iteration":944,"passed_time":48.05747788,"remaining_time":2.796996067},
{"learn":[7.441369328],"iteration":945,"passed_time":48.10628585,"remaining_time":2.746024774},
{"learn":[7.439677092],"iteration":946,"passed_time":48.155758,"remaining_time":2.695095221},
{"learn":[7.435065979],"iteration":947,"passed_time":48.20489326,"remaining_time":2.644150263},
{"learn":[7.431377025],"iteration":948,"passed_time":48.25392386,"remaining_time":2.593203495},
{"learn":[7.427807034],"iteration":949,"passed_time":48.30366671,"remaining_time":2.542298248},
{"learn":[7.426003261],"iteration":950,"passed_time":48.35397438,"remaining_time":2.491424547},
{"learn":[7.421087193],"iteration":951,"passed_time":48.40467526,"remaining_time":2.440571862},
{"learn":[7.41902434],"iteration":952,"passed_time":48.4549102,"remaining_time":2.389696516},
{"learn":[7.417723662],"iteration":953,"passed_time":48.50564227,"remaining_time":2.338846482},
{"learn":[7.416711681],"iteration":954,"passed_time":48.55554895,"remaining_time":2.287957804},
{"learn":[7.413526679],"iteration":955,"passed_time":48.60797541,"remaining_time":2.237187153},
{"learn":[7.408546691],"iteration":956,"passed_time":48.65800176,"remaining_time":2.186305199},
{"learn":[7.407186142],"iteration":957,"passed_time":48.70755301,"remaining_time":2.135404203},
{"learn":[7.404421687],"iteration":958,"passed_time":48.75622627,"remaining_time":2.084468485},
{"learn":[7.400601358],"iteration":959,"passed_time":48.80480141,"remaining_time":2.033533392},
{"learn":[7.397695752],"iteration":960,"passed_time":48.85321562,"remaining_time":1.98259668},
{"learn":[7.392575854],"iteration":961,"passed_time":48.90165818,"remaining_time":1.931666331},
{"learn":[7.388763909],"iteration":962,"passed_time":48.95058476,"remaining_time":1.880759747},
{"learn":[7.383509297],"iteration":963,"passed_time":48.99930527,"remaining_time":1.829849574},
{"learn":[7.381620158],"iteration":964,"passed_time":49.04746806,"remaining_time":1.778923712},
{"learn":[7.378924081],"iteration":965,"passed_time":49.09568965,"remaining_time":1.72800564},
{"learn":[7.377110455],"iteration":966,"passed_time":49.14445675,"remaining_time":1.677111761},
{"learn":[7.373007054],"iteration":967,"passed_time":49.19252583,"remaining_time":1.626199201},
{"learn":[7.369261072],"iteration":968,"passed_time":49.24103134,"remaining_time":1.575306472},
{"learn":[7.367260281],"iteration":969,"passed_time":49.28929058,"remaining_time":1.524411049},
{"learn":[7.364064345],"iteration":970,"passed_time":49.33816871,"remaining_time":1.473539539},
{"learn":[7.360648661],"iteration":971,"passed_time":49.38697354,"remaining_time":1.42267002},
{"learn":[7.359564419],"iteration":972,"passed_time":49.4356712,"remaining_time":1.37180177},
{"learn":[7.356340672],"iteration":973,"passed_time":49.49173804,"remaining_time":1.321134691},
{"learn":[7.354116138],"iteration":974,"passed_time":49.53991225,"remaining_time":1.27025416},
{"learn":[7.350046893],"iteration":975,"passed_time":49.58837248,"remaining_time":1.219386208},
{"learn":[7.34670366],"iteration":976,"passed_time":49.63725863,"remaining_time":1.168533212},
{"learn":[7.345201266],"iteration":977,"passed_time":49.68554493,"remaining_time":1.117670745},
{"learn":[7.344661868],"iteration":978,"passed_time":49.73402158,"remaining_time":1.066817623},
{"learn":[7.34178834],"iteration":979,"passed_time":49.78250214,"remaining_time":1.015969431},
{"learn":[7.338043612],"iteration":980,"passed_time":49.83145159,"remaining_time":0.9651351481},
{"learn":[7.335819869],"iteration":981,"passed_time":49.87955138,"remaining_time":0.9142891292},
{"learn":[7.332329155],"iteration":982,"passed_time":49.92821309,"remaining_time":0.8634584156},
{"learn":[7.329631019],"iteration":983,"passed_time":49.97699854,"remaining_time":0.8126341227},
{"learn":[7.326576319],"iteration":984,"passed_time":50.02589014,"remaining_time":0.7618155859},
{"learn":[7.321746777],"iteration":985,"passed_time":50.07400408,"remaining_time":0.7109899159},
{"learn":[7.320285415],"iteration":986,"passed_time":50.1233176,"remaining_time":0.6601855408},
{"learn":[7.318382265],"iteration":987,"passed_time":50.17069313,"remaining_time":0.6093606454},
{"learn":[7.313559829],"iteration":988,"passed_time":50.21986011,"remaining_time":0.5585626503},
{"learn":[7.311974947],"iteration":989,"passed_time":50.27002525,"remaining_time":0.5077780328},
{"learn":[7.309981642],"iteration":990,"passed_time":50.3198649,"remaining_time":0.4569917095},
{"learn":[7.308816313],"iteration":991,"passed_time":50.368525,"remaining_time":0.4061977822},
{"learn":[7.307856121],"iteration":992,"passed_time":50.41639085,"remaining_time":0.3554025538},
{"learn":[7.306283727],"iteration":993,"passed_time":50.46453007,"remaining_time":0.3046148697},
{"learn":[7.303892956],"iteration":994,"passed_time":50.51362925,"remaining_time":0.2538373329},
{"learn":[7.299494257],"iteration":995,"passed_time":50.56216846,"remaining_time":0.2030609175},
{"learn":[7.296864324],"iteration":996,"passed_time":50.61121846,"remaining_time":0.152290527},
{"learn":[7.292359138],"iteration":997,"passed_time":50.65994722,"remaining_time":0.1015229403},
{"learn":[7.290521014],"iteration":998,"passed_time":50.70913916,"remaining_time":0.05075989906},
{"learn":[7.287036724],"iteration":999,"passed_time":50.75823467,"remaining_time":0}
]}